{
    "id": 4095,
    "name": "4095",
    "form": "default",
    "main_type": {
        "id": 7,
        "name": "Ice",
        "localized": {
            "zh": "冰"
        }
    },
    "sub_type": null,
    "default_legacy_type": {
        "id": 7,
        "name": "Ice",
        "localized": {
            "zh": "冰"
        }
    },
    "leader_potential": false,
    "is_leader_form": true,
    "preferred_attack_style": "Both",
    "localized": {
        "zh": {
            "name": "饮雪狂兽"
        }
    },
    "implemented": false,
    "base_hp": 0,
    "base_phy_atk": 0,
    "base_mag_atk": 0,
    "base_phy_def": 0,
    "base_mag_def": 0,
    "base_spd": 0,
    "evolves_from_id": null,
    "species": {
        "id": 4095,
        "name": "4095",
        "localized": {
            "zh": "饮雪狂兽"
        }
    },
    "trait": {
        "id": 299002,
        "name": "？？？",
        "description": "散发着危险气息的精灵，看不出特性",
        "icon_id": "img_wenhao",
        "localized": {
            "zh": {
                "name": "？？？",
                "description": "散发着危险气息的精灵，看不出特性"
            }
        }
    },
    "move_pool": [],
    "move_stones": [],
    "legacy_moves": [],
    "evolution_tree": {
        "stages": [
            {
                "depth": 0,
                "monsters": [
                    {
                        "id": 4095,
                        "name": "4095",
                        "form": "default",
                        "localized": {
                            "zh": {
                                "name": "饮雪狂兽"
                            }
                        },
                        "is_leader_form": true,
                        "main_type": {
                            "id": 7,
                            "name": "Ice",
                            "localized": {
                                "zh": "冰"
                            }
                        },
                        "sub_type": null,
                        "evolution_conditions": []
                    }
                ],
                "is_leader_stage": true
            },
            {
                "depth": 1,
                "is_leader_stage": true,
                "monsters": [
                    {
                        "id": 4095,
                        "name": "4095",
                        "form": "default",
                        "localized": {
                            "zh": {
                                "name": "饮雪狂兽"
                            }
                        },
                        "is_leader_form": true,
                        "main_type": {
                            "id": 7,
                            "name": "Ice",
                            "localized": {
                                "zh": "冰"
                            }
                        },
                        "sub_type": null,
                        "evolution_conditions": []
                    }
                ]
            }
        ],
        "max_depth": 1,
        "total_unique_monsters": 1,
        "species_id": 4095,
        "current_monster_id": 4095
    },
    "world_profile": {
        "type_desc": null,
        "description_habitat": null,
        "introduction": "只有当契约者死亡的时候才会寻找下一位契约者。假如原契约者活着，但它们必须更换契约者的话，可能会自我了结生命。魔法部认证的精灵契约经销商永远不会售卖和雪灵的契约。",
        "refresh_locations": [],
        "movement_type": "步行",
        "classis_id": 6,
        "classis_name": "自然类精灵",
        "handbook_area_ids": []
    },
    "catch_info": null,
    "breeding": null,
    "breeding_profile": {
        "pet_base_id": 4095,
        "egg_groups": [],
        "proportion_male": 5,
        "male_rate": 50,
        "female_rate": 50
    }
}
