{
  "RocoDataRows": {
    "10140001": {
      "id": 10140001,
      "group_id": 1014001,
      "memo": "JQ01_洞窟_灵魂边境同行_星灵",
      "npc_icon": "Texture2D'/Game/NewRoco/Modules/System/BigMap/Raw/Atlas/WorldMapNpc/Frames/starsouls_01.starsouls_01'",
      "npc_name": "？？？",
      "ui_type": "UI_DIALOGUE",
      "text": "洛克王国...",
      "text_voice": "dialogwish22",
      "next_id": 10140021,
      "stay_time": 5,
      "priority": 1
    },
    "10140002": {
      "id": 10140002,
      "group_id": 1014001,
      "memo": "JQ01_洞窟_灵魂边境同行_星灵",
      "npc_icon": "Texture2D'/Game/NewRoco/Modules/System/BigMap/Raw/Atlas/WorldMapNpc/Frames/starsouls_01.starsouls_01'",
      "npc_name": "？？？",
      "ui_type": "UI_DIALOGUE",
      "text": "洛克王国！",
      "text_voice": "dialogwish23",
      "next_id": 10140010,
      "stay_time": 5,
      "priority": 1
    },
    "10140003": {
      "id": 10140003,
      "group_id": 1014001,
      "memo": "JQ01_洞窟_灵魂边境同行_小男孩７",
      "npc_icon": "Texture2D'/Game/NewRoco/Modules/System/BigMap/Raw/Atlas/WorldMapNpc/Frames/threshold_soul1.threshold_soul1'",
      "npc_name": "？？？",
      "ui_type": "UI_DIALOGUE",
      "text": "在维苏威火山的地心，我会揭开火焰喷发的秘密",
      "text_voice": "dialogwish03",
      "next_id": 10140006,
      "stay_time": 10,
      "priority": 1
    },
    "10140004": {
      "id": 10140004,
      "group_id": 1014001,
      "memo": "JQ01_洞窟_灵魂边境同行_小男孩９",
      "npc_icon": "Texture2D'/Game/NewRoco/Modules/System/BigMap/Raw/Atlas/WorldMapNpc/Frames/threshold_soul2.threshold_soul2'",
      "npc_name": "？？？",
      "ui_type": "UI_DIALOGUE",
      "text": "记得来我家串门哦，我的精灵一直在等待你的挑战。",
      "text_voice": "dialogwish05",
      "next_id": 10140024,
      "stay_time": 10,
      "priority": 1
    },
    "10140005": {
      "id": 10140005,
      "group_id": 1014001,
      "memo": "JQ01_洞窟_灵魂边境同行_小男孩13",
      "npc_icon": "Texture2D'/Game/NewRoco/Modules/System/BigMap/Raw/Atlas/WorldMapNpc/Frames/threshold_soul5.threshold_soul5'",
      "npc_name": "？？？",
      "ui_type": "UI_DIALOGUE",
      "text": "听说玄玉岛，住着一只比石头活得还久的大乌龟哦!",
      "text_voice": "dialogwish09",
      "next_id": 10140025,
      "stay_time": 10,
      "priority": 1
    },
    "10140006": {
      "id": 10140006,
      "group_id": 1014001,
      "memo": "JQ01_洞窟_灵魂边境同行_小男孩15",
      "npc_icon": "Texture2D'/Game/NewRoco/Modules/System/BigMap/Raw/Atlas/WorldMapNpc/Frames/threshold_soul6.threshold_soul6'",
      "npc_name": "？？？",
      "ui_type": "UI_DIALOGUE",
      "text": "再有一天!我的蛋就能孵出会冰晶结界的喵喵啦!",
      "text_voice": "dialogwish11",
      "next_id": 10140004,
      "stay_time": 10,
      "priority": 1
    },
    "10140007": {
      "id": 10140007,
      "group_id": 1014001,
      "memo": "JQ01_洞窟_灵魂边境同行_小男孩19",
      "npc_icon": "Texture2D'/Game/NewRoco/Modules/System/BigMap/Raw/Atlas/WorldMapNpc/Frames/starsouls_01.starsouls_01'",
      "npc_name": "？？？",
      "ui_type": "UI_DIALOGUE",
      "text": "圣龙骑士，我们需要你!",
      "text_voice": "dialogwish15",
      "next_id": 10140027,
      "stay_time": 7,
      "priority": 1
    },
    "10140008": {
      "id": 10140008,
      "group_id": 1014001,
      "memo": "JQ01_洞窟_灵魂边境同行_小男孩23",
      "npc_icon": "Texture2D'/Game/NewRoco/Modules/System/BigMap/Raw/Atlas/WorldMapNpc/Frames/starsouls_01.starsouls_01'",
      "npc_name": "？？？",
      "ui_type": "UI_DIALOGUE",
      "text": "梦想无论怎样模糊，却依然潜伏在我们心底",
      "text_voice": "dialogwish19",
      "next_id": 10140028,
      "stay_time": 10,
      "priority": 1
    },
    "10140009": {
      "id": 10140009,
      "group_id": 1014001,
      "memo": "JQ01_洞窟_灵魂边境同行_小男孩25",
      "npc_icon": "Texture2D'/Game/NewRoco/Modules/System/BigMap/Raw/Atlas/WorldMapNpc/Frames/threshold_soul1.threshold_soul1'",
      "npc_name": "？？？",
      "ui_type": "UI_DIALOGUE",
      "text": "羡慕别人的时候，应该自己加倍努力哦!",
      "text_voice": "dialogwish21",
      "next_id": 10140029,
      "stay_time": 7,
      "priority": 1
    },
    "10140010": {
      "id": 10140010,
      "group_id": 1014001,
      "memo": "JQ01_洞窟_灵魂边境同行_小男孩29（last4）",
      "npc_icon": "Texture2D'/Game/NewRoco/Modules/System/BigMap/Raw/Atlas/WorldMapNpc/Frames/threshold_soul2.threshold_soul2'",
      "npc_name": "？？？",
      "ui_type": "UI_DIALOGUE",
      "text": "洛克王国！",
      "text_voice": "dialogwish24",
      "stay_time": 5,
      "priority": 1
    },
    "10140021": {
      "id": 10140021,
      "group_id": 1014001,
      "memo": "JQ01_洞窟_灵魂边境同行_小女孩2（last2）",
      "npc_icon": "Texture2D'/Game/NewRoco/Modules/System/BigMap/Raw/Atlas/WorldMapNpc/Frames/threshold_soul3.threshold_soul3'",
      "npc_name": "？？？",
      "ui_type": "UI_DIALOGUE",
      "text": "洛克王国...",
      "text_voice": "dialogwish25",
      "next_id": 10140002,
      "stay_time": 5,
      "priority": 1
    },
    "10140022": {
      "id": 10140022,
      "group_id": 1014001,
      "memo": "JQ01_洞窟_灵魂边境同行_小女孩６",
      "npc_icon": "Texture2D'/Game/NewRoco/Modules/System/BigMap/Raw/Atlas/WorldMapNpc/Frames/starsouls_01.starsouls_01'",
      "npc_name": "？？？",
      "ui_type": "UI_DIALOGUE",
      "text": "我不会告诉任何人，幽影峡谷隐藏着复活的秘密!",
      "text_voice": "dialogwish02",
      "next_id": 10140023,
      "stay_time": 10,
      "priority": 1
    },
    "10140023": {
      "id": 10140023,
      "group_id": 1014001,
      "memo": "JQ01_洞窟_灵魂边境同行_小女孩10",
      "npc_icon": "Texture2D'/Game/NewRoco/Modules/System/BigMap/Raw/Atlas/WorldMapNpc/Frames/starsouls_01.starsouls_01'",
      "npc_name": "？？？",
      "ui_type": "UI_DIALOGUE",
      "text": "要向山姆大叔问声好，然后再买许多许多种子！",
      "text_voice": "dialogwish06",
      "next_id": 10140043,
      "stay_time": 10,
      "priority": 1
    },
    "10140024": {
      "id": 10140024,
      "group_id": 1014001,
      "memo": "JQ01_洞窟_灵魂边境同行_小女孩12",
      "npc_icon": "Texture2D'/Game/NewRoco/Modules/System/BigMap/Raw/Atlas/WorldMapNpc/Frames/starsouls_01.starsouls_01'",
      "npc_name": "？？？",
      "ui_type": "UI_DIALOGUE",
      "text": "有精灵陪我一起潜水吗？一起去探索亚特兰蒂斯吧！",
      "text_voice": "dialogwish08",
      "next_id": 10140005,
      "stay_time": 10,
      "priority": 1
    },
    "10140025": {
      "id": 10140025,
      "group_id": 1014001,
      "memo": "JQ01_洞窟_灵魂边境同行_小女孩16",
      "npc_icon": "Texture2D'/Game/NewRoco/Modules/System/BigMap/Raw/Atlas/WorldMapNpc/Frames/threshold_soul8.threshold_soul8'",
      "npc_name": "？？？",
      "ui_type": "UI_DIALOGUE",
      "text": "希望我的好朋友乐维，能够等到爸爸的拥抱…",
      "text_voice": "dialogwish12",
      "next_id": 10140045,
      "stay_time": 10,
      "priority": 1
    },
    "10140026": {
      "id": 10140026,
      "group_id": 1014001,
      "memo": "JQ01_洞窟_灵魂边境同行_小女孩18",
      "npc_icon": "Texture2D'/Game/NewRoco/Modules/System/BigMap/Raw/Atlas/WorldMapNpc/Frames/threshold_soul7.threshold_soul7'",
      "npc_name": "？？？",
      "ui_type": "UI_DIALOGUE",
      "text": "总有一天，我的哈古利乌会飞上天空城最高的藤蔓。",
      "text_voice": "dialogwish14",
      "next_id": 10140044,
      "stay_time": 10,
      "priority": 1
    },
    "10140027": {
      "id": 10140027,
      "group_id": 1014001,
      "memo": "JQ01_洞窟_灵魂边境同行_小女孩20",
      "npc_icon": "Texture2D'/Game/NewRoco/Modules/System/BigMap/Raw/Atlas/WorldMapNpc/Frames/starsouls_01.starsouls_01'",
      "npc_name": "？？？",
      "ui_type": "UI_DIALOGUE",
      "text": "面对未知的困难，即使再迷茫，也要迎难而上！",
      "text_voice": "dialogwish16",
      "next_id": 10140009,
      "stay_time": 10,
      "priority": 1
    },
    "10140028": {
      "id": 10140028,
      "group_id": 1014001,
      "memo": "JQ01_洞窟_灵魂边境同行_小女孩22",
      "npc_icon": "Texture2D'/Game/NewRoco/Modules/System/BigMap/Raw/Atlas/WorldMapNpc/Frames/starsouls_01.starsouls_01'",
      "npc_name": "？？？",
      "ui_type": "UI_DIALOGUE",
      "text": "真正的友情，即使不说出口，也会沉甸甸地落在心头",
      "text_voice": "dialogwish18",
      "next_id": 10140007,
      "stay_time": 10,
      "priority": 1
    },
    "10140029": {
      "id": 10140029,
      "group_id": 1014001,
      "memo": "JQ01_洞窟_灵魂边境同行_小女孩24",
      "npc_icon": "Texture2D'/Game/NewRoco/Modules/System/BigMap/Raw/Atlas/WorldMapNpc/Frames/threshold_soul4.threshold_soul4'",
      "npc_name": "？？？",
      "ui_type": "UI_DIALOGUE",
      "text": "要相信，你从来不是一个人在战斗!",
      "text_voice": "dialogwish20",
      "next_id": 10140001,
      "stay_time": 10,
      "priority": 1
    },
    "10140030": {
      "id": 10140030,
      "group_id": 1014001,
      "memo": "JQ01_洞窟_灵魂边境同行_小女孩27",
      "npc_icon": "Texture2D'/Game/NewRoco/Modules/System/BigMap/Raw/Atlas/WorldMapNpc/Frames/threshold_soul8.threshold_soul8'",
      "npc_name": "？？？",
      "ui_type": "UI_DIALOGUE",
      "text": "洛克王国…（没被外链）",
      "text_voice": "dialogwish22",
      "next_id": 10140049,
      "stay_time": 5,
      "priority": 1
    },
    "10140041": {
      "id": 10140041,
      "group_id": 1014001,
      "memo": "JQ01_洞窟_灵魂边境同行_星灵3（叠加）",
      "npc_icon": "Texture2D'/Game/NewRoco/Modules/System/BigMap/Raw/Atlas/WorldMapNpc/Frames/starsouls_01.starsouls_01'",
      "npc_name": "？？？",
      "ui_type": "UI_DIALOGUE",
      "text": "洛克王国！(没被外链）",
      "text_voice": "dialogwish23",
      "next_id": 10140002,
      "stay_time": 5,
      "priority": 1
    },
    "10140042": {
      "id": 10140042,
      "group_id": 1014001,
      "memo": "JQ01_洞窟_灵魂边境同行_星灵5",
      "npc_icon": "Texture2D'/Game/NewRoco/Modules/System/BigMap/Raw/Atlas/WorldMapNpc/Frames/starsouls_01.starsouls_01'",
      "npc_name": "？？？",
      "ui_type": "UI_DIALOGUE",
      "text": "好想去枫雪镇啊，说不定能见到那只冰龙的身影！",
      "text_voice": "dialogwish01",
      "next_id": 10140022,
      "stay_time": 10,
      "condition": 5,
      "condition_parameter": [
        1
      ],
      "priority": 1
    },
    "10140043": {
      "id": 10140043,
      "group_id": 1014001,
      "memo": "JQ01_洞窟_灵魂边境同行_星灵８",
      "npc_icon": "Texture2D'/Game/NewRoco/Modules/System/BigMap/Raw/Atlas/WorldMapNpc/Frames/threshold_soul4.threshold_soul4'",
      "npc_name": "？？？",
      "ui_type": "UI_DIALOGUE",
      "text": "去到糖果迷城，我们就可以获得甜品精灵了吧!",
      "text_voice": "dialogwish04",
      "next_id": 10140003,
      "stay_time": 10,
      "priority": 1
    },
    "10140044": {
      "id": 10140044,
      "group_id": 1014001,
      "memo": "JQ01_洞窟_灵魂边境同行_星灵11",
      "npc_icon": "Texture2D'/Game/NewRoco/Modules/System/BigMap/Raw/Atlas/WorldMapNpc/Frames/threshold_soul6.threshold_soul6'",
      "npc_name": "？？？",
      "ui_type": "UI_DIALOGUE",
      "text": "记得以前的植物园吗?最可爱的艾迪和她的小狗。",
      "text_voice": "dialogwish07",
      "next_id": 10140046,
      "stay_time": 10,
      "priority": 1
    },
    "10140045": {
      "id": 10140045,
      "group_id": 1014001,
      "memo": "JQ01_洞窟_灵魂边境同行_星灵14",
      "npc_icon": "Texture2D'/Game/NewRoco/Modules/System/BigMap/Raw/Atlas/WorldMapNpc/Frames/threshold_soul7.threshold_soul7'",
      "npc_name": "？？？",
      "ui_type": "UI_DIALOGUE",
      "text": "今天有去拉布朗矿山挖金子吗?挣钱很重要啊。",
      "text_voice": "dialogwish10",
      "next_id": 10140026,
      "stay_time": 10,
      "priority": 1
    },
    "10140046": {
      "id": 10140046,
      "group_id": 1014001,
      "memo": "JQ01_洞窟_灵魂边境同行_星灵17",
      "npc_icon": "Texture2D'/Game/NewRoco/Modules/System/BigMap/Raw/Atlas/WorldMapNpc/Frames/starsouls_01.starsouls_01'",
      "npc_name": "？？？",
      "ui_type": "UI_DIALOGUE",
      "text": "阿布，站起来！相信自己，你是最勇敢的精灵!",
      "text_voice": "dialogwish13",
      "next_id": 10140047,
      "stay_time": 10,
      "priority": 1
    },
    "10140047": {
      "id": 10140047,
      "group_id": 1014001,
      "memo": "JQ01_洞窟_灵魂边境同行_星灵21",
      "npc_icon": "Texture2D'/Game/NewRoco/Modules/System/BigMap/Raw/Atlas/WorldMapNpc/Frames/threshold_soul5.threshold_soul5'",
      "npc_name": "？？？",
      "ui_type": "UI_DIALOGUE",
      "text": "特别的天赋，只有用在光明的地方才能成为最强大的力量!",
      "text_voice": "dialogwish17",
      "next_id": 10140008,
      "stay_time": 10,
      "priority": 1
    },
    "10140048": {
      "id": 10140048,
      "group_id": 1014001,
      "memo": "JQ01_洞窟_灵魂边境同行_星灵26",
      "npc_icon": "Texture2D'/Game/NewRoco/Modules/System/BigMap/Raw/Atlas/WorldMapNpc/Frames/starsouls_01.starsouls_01'",
      "npc_name": "？？？",
      "ui_type": "UI_DIALOGUE",
      "text": "洛克王国…（没被外链）",
      "next_id": 10140030,
      "stay_time": 5,
      "priority": 1
    },
    "10140049": {
      "id": 10140049,
      "group_id": 1014001,
      "memo": "JQ01_洞窟_灵魂边境同行_星灵28",
      "npc_icon": "Texture2D'/Game/NewRoco/Modules/System/BigMap/Raw/Atlas/WorldMapNpc/Frames/starsouls_01.starsouls_01'",
      "npc_name": "？？？",
      "ui_type": "UI_DIALOGUE",
      "text": "洛克王国！（没被外链）",
      "next_id": 10140010,
      "stay_time": 5,
      "priority": 1
    },
    "10140050": {
      "id": 10140050,
      "group_id": 1014001,
      "memo": "JQ01_洞窟_灵魂边境同行_星灵00（保底）",
      "npc_icon": "Texture2D'/Game/NewRoco/Modules/System/BigMap/Raw/Atlas/WorldMapNpc/Frames/10062.10062'",
      "npc_name": "星灵",
      "ui_type": "UI_STATE",
      "text": "同行中…",
      "next_id": 10140042,
      "stay_time": -1,
      "priority": 1
    },
    "10140060": {
      "id": 10140060,
      "group_id": 1014002,
      "memo": "JQ01_洞窟_灵魂边境同行_星灵",
      "npc_icon": "Texture2D'/Game/NewRoco/Modules/System/BigMap/Raw/Atlas/WorldMapNpc/Frames/starsouls_01.starsouls_01'",
      "npc_name": "灵魂共鸣",
      "ui_type": "UI_DIALOGUE",
      "text": "前面的别跑太快，手快牵不住啦",
      "next_id": 10140061,
      "stay_time": 5,
      "priority": 1
    },
    "10140061": {
      "id": 10140061,
      "group_id": 1014002,
      "memo": "JQ01_洞窟_灵魂边境同行_小男孩７",
      "npc_icon": "Texture2D'/Game/NewRoco/Modules/System/BigMap/Raw/Atlas/WorldMapNpc/Frames/threshold_soul1.threshold_soul1'",
      "npc_name": "灵魂共鸣",
      "ui_type": "UI_DIALOGUE",
      "text": "我的精灵能坐两个人，要不要上来",
      "next_id": 10140062,
      "stay_time": 5,
      "priority": 1
    },
    "10140062": {
      "id": 10140062,
      "group_id": 1014002,
      "memo": "JQ01_洞窟_灵魂边境同行_小男孩９",
      "npc_icon": "Texture2D'/Game/NewRoco/Modules/System/BigMap/Raw/Atlas/WorldMapNpc/Frames/threshold_soul2.threshold_soul2'",
      "npc_name": "灵魂共鸣",
      "ui_type": "UI_DIALOGUE",
      "text": "噜噜向导的护心毛，绒绒好温暖，好想拔一根",
      "next_id": 10140063,
      "stay_time": 5,
      "priority": 1
    },
    "10140063": {
      "id": 10140063,
      "group_id": 1014002,
      "memo": "JQ01_洞窟_灵魂边境同行_星灵17",
      "npc_icon": "Texture2D'/Game/NewRoco/Modules/System/BigMap/Raw/Atlas/WorldMapNpc/Frames/starsouls_01.starsouls_01'",
      "npc_name": "灵魂共鸣",
      "ui_type": "UI_DIALOGUE",
      "text": "听说丰裕谷的大树下面，埋着一位鸭富商的宝藏",
      "next_id": 10140064,
      "stay_time": 5,
      "priority": 1
    },
    "10140064": {
      "id": 10140064,
      "group_id": 1014002,
      "memo": "JQ01_洞窟_灵魂边境同行_星灵21",
      "npc_icon": "Texture2D'/Game/NewRoco/Modules/System/BigMap/Raw/Atlas/WorldMapNpc/Frames/threshold_soul5.threshold_soul5'",
      "npc_name": "灵魂共鸣",
      "ui_type": "UI_DIALOGUE",
      "text": "古老的风眠圣所，其实是大机器精灵帮忙造的哦",
      "next_id": 10140065,
      "stay_time": 5,
      "priority": 1
    },
    "10140065": {
      "id": 10140065,
      "group_id": 1014002,
      "memo": "JQ01_洞窟_灵魂边境同行_小女孩22",
      "npc_icon": "Texture2D'/Game/NewRoco/Modules/System/BigMap/Raw/Atlas/WorldMapNpc/Frames/starsouls_01.starsouls_01'",
      "npc_name": "灵魂共鸣",
      "ui_type": "UI_DIALOGUE",
      "text": "站在岚羽峰的山顶，就会听到古老精灵发出的叹息",
      "next_id": 10140066,
      "stay_time": 5,
      "priority": 1
    },
    "10140066": {
      "id": 10140066,
      "group_id": 1014002,
      "memo": "JQ01_洞窟_灵魂边境同行_小女孩24",
      "npc_icon": "Texture2D'/Game/NewRoco/Modules/System/BigMap/Raw/Atlas/WorldMapNpc/Frames/threshold_soul4.threshold_soul4'",
      "npc_name": "灵魂共鸣",
      "ui_type": "UI_DIALOGUE",
      "text": "一起去参加可可果节吧，比比谁喝的可瓦斯更多~",
      "next_id": 10140067,
      "stay_time": 5,
      "priority": 1
    },
    "10140067": {
      "id": 10140067,
      "group_id": 1014002,
      "memo": "JQ01_洞窟_灵魂边境同行_星灵",
      "npc_icon": "Texture2D'/Game/NewRoco/Modules/System/BigMap/Raw/Atlas/WorldMapNpc/Frames/starsouls_01.starsouls_01'",
      "npc_name": "灵魂共鸣",
      "ui_type": "UI_DIALOGUE",
      "text": "看到我的留言羽毛了吗，下个藏宝点在这里",
      "next_id": 10140068,
      "stay_time": 5,
      "priority": 1
    },
    "10140068": {
      "id": 10140068,
      "group_id": 1014002,
      "memo": "JQ01_洞窟_灵魂边境同行_小男孩７",
      "npc_icon": "Texture2D'/Game/NewRoco/Modules/System/BigMap/Raw/Atlas/WorldMapNpc/Frames/threshold_soul1.threshold_soul1'",
      "npc_name": "灵魂共鸣",
      "ui_type": "UI_DIALOGUE",
      "text": "板板壳，看我镜头，1,2,3——！",
      "next_id": 10140069,
      "stay_time": 5,
      "priority": 1
    },
    "10140069": {
      "id": 10140069,
      "group_id": 1014002,
      "memo": "JQ01_洞窟_灵魂边境同行_小男孩９",
      "npc_icon": "Texture2D'/Game/NewRoco/Modules/System/BigMap/Raw/Atlas/WorldMapNpc/Frames/threshold_soul2.threshold_soul2'",
      "npc_name": "灵魂共鸣",
      "ui_type": "UI_DIALOGUE",
      "text": "希望……今天家里的精灵们没有打架吧……",
      "next_id": 10140070,
      "stay_time": 5,
      "priority": 1
    },
    "10140070": {
      "id": 10140070,
      "group_id": 1014002,
      "memo": "JQ01_洞窟_灵魂边境同行_星灵17",
      "npc_icon": "Texture2D'/Game/NewRoco/Modules/System/BigMap/Raw/Atlas/WorldMapNpc/Frames/starsouls_01.starsouls_01'",
      "npc_name": "灵魂共鸣",
      "ui_type": "UI_DIALOGUE",
      "text": "听说邻居家的小洛克造了地下室，好想去看看",
      "next_id": 10140071,
      "stay_time": 5,
      "priority": 1
    },
    "10140071": {
      "id": 10140071,
      "group_id": 1014002,
      "memo": "JQ01_洞窟_灵魂边境同行_星灵21",
      "npc_icon": "Texture2D'/Game/NewRoco/Modules/System/BigMap/Raw/Atlas/WorldMapNpc/Frames/threshold_soul5.threshold_soul5'",
      "npc_name": "灵魂共鸣",
      "ui_type": "UI_DIALOGUE",
      "text": "看不见了……我的嘟嘟锅，怎么跑到了我的头上",
      "next_id": 10140072,
      "stay_time": 5,
      "priority": 1
    },
    "10140072": {
      "id": 10140072,
      "group_id": 1014002,
      "memo": "JQ01_洞窟_灵魂边境同行_小女孩22",
      "npc_icon": "Texture2D'/Game/NewRoco/Modules/System/BigMap/Raw/Atlas/WorldMapNpc/Frames/starsouls_01.starsouls_01'",
      "npc_name": "灵魂共鸣",
      "ui_type": "UI_DIALOGUE",
      "text": "在野外摘了一朵蘑菇，然后看到好多好多鸭子",
      "next_id": 10140073,
      "stay_time": 5,
      "priority": 1
    },
    "10140073": {
      "id": 10140073,
      "group_id": 1014002,
      "memo": "JQ01_洞窟_灵魂边境同行_小女孩24",
      "npc_icon": "Texture2D'/Game/NewRoco/Modules/System/BigMap/Raw/Atlas/WorldMapNpc/Frames/threshold_soul4.threshold_soul4'",
      "npc_name": "灵魂共鸣",
      "ui_type": "UI_DIALOGUE",
      "text": "他是最伟大的国王，亦是最好的孩子",
      "next_id": 10140074,
      "stay_time": 5,
      "priority": 1
    },
    "10140074": {
      "id": 10140074,
      "group_id": 1014002,
      "memo": "JQ01_洞窟_灵魂边境同行_星灵",
      "npc_icon": "Texture2D'/Game/NewRoco/Modules/System/BigMap/Raw/Atlas/WorldMapNpc/Frames/starsouls_01.starsouls_01'",
      "npc_name": "灵魂共鸣",
      "ui_type": "UI_DIALOGUE",
      "text": "约定最终会被忘记，只有孩子们，才会坚信它的存在",
      "next_id": 10140075,
      "stay_time": 5,
      "priority": 1
    },
    "10140075": {
      "id": 10140075,
      "group_id": 1014002,
      "memo": "JQ01_洞窟_灵魂边境同行_小男孩７",
      "npc_icon": "Texture2D'/Game/NewRoco/Modules/System/BigMap/Raw/Atlas/WorldMapNpc/Frames/threshold_soul1.threshold_soul1'",
      "npc_name": "灵魂共鸣",
      "ui_type": "UI_DIALOGUE",
      "text": "灵魂，是每个生命体身上的最珍贵之物",
      "next_id": 10140076,
      "stay_time": 5,
      "priority": 1
    },
    "10140076": {
      "id": 10140076,
      "group_id": 1014002,
      "memo": "JQ01_洞窟_灵魂边境同行_小男孩９",
      "npc_icon": "Texture2D'/Game/NewRoco/Modules/System/BigMap/Raw/Atlas/WorldMapNpc/Frames/threshold_soul2.threshold_soul2'",
      "npc_name": "灵魂共鸣",
      "ui_type": "UI_DIALOGUE",
      "text": "难的从来不是复苏，而是复苏的代价",
      "next_id": 10140077,
      "stay_time": 5,
      "priority": 1
    },
    "10140077": {
      "id": 10140077,
      "group_id": 1014002,
      "memo": "JQ01_洞窟_灵魂边境同行_星灵17",
      "npc_icon": "Texture2D'/Game/NewRoco/Modules/System/BigMap/Raw/Atlas/WorldMapNpc/Frames/starsouls_01.starsouls_01'",
      "npc_name": "灵魂共鸣",
      "ui_type": "UI_DIALOGUE",
      "text": "如果不认识，再认识一遍不就好了",
      "next_id": 10140078,
      "stay_time": 5,
      "priority": 1
    },
    "10140078": {
      "id": 10140078,
      "group_id": 1014002,
      "memo": "JQ01_洞窟_灵魂边境同行_星灵21",
      "npc_icon": "Texture2D'/Game/NewRoco/Modules/System/BigMap/Raw/Atlas/WorldMapNpc/Frames/threshold_soul5.threshold_soul5'",
      "npc_name": "灵魂共鸣",
      "ui_type": "UI_DIALOGUE",
      "text": "记得那么多事情的我，一定会再成为它最好的朋友",
      "next_id": 10140079,
      "stay_time": 5,
      "priority": 1
    },
    "10140079": {
      "id": 10140079,
      "group_id": 1014002,
      "memo": "JQ01_洞窟_灵魂边境同行_小女孩22",
      "npc_icon": "Texture2D'/Game/NewRoco/Modules/System/BigMap/Raw/Atlas/WorldMapNpc/Frames/starsouls_01.starsouls_01'",
      "npc_name": "灵魂共鸣",
      "ui_type": "UI_DIALOGUE",
      "text": "这就是他们所说的契约吗，是你，让我感受到了这种奇妙的力量",
      "next_id": 10140080,
      "stay_time": 5,
      "priority": 1
    },
    "10140080": {
      "id": 10140080,
      "group_id": 1014002,
      "memo": "JQ01_洞窟_灵魂边境同行_小女孩24",
      "npc_icon": "Texture2D'/Game/NewRoco/Modules/System/BigMap/Raw/Atlas/WorldMapNpc/Frames/threshold_soul4.threshold_soul4'",
      "npc_name": "灵魂共鸣",
      "ui_type": "UI_DIALOGUE",
      "text": "哪怕是如此弱小的我，也想要将那光芒，继承下去",
      "next_id": 10140081,
      "stay_time": 5,
      "priority": 1
    },
    "10140081": {
      "id": 10140081,
      "group_id": 1014002,
      "memo": "JQ01_洞窟_灵魂边境同行_星灵",
      "npc_icon": "Texture2D'/Game/NewRoco/Modules/System/BigMap/Raw/Atlas/WorldMapNpc/Frames/starsouls_01.starsouls_01'",
      "npc_name": "灵魂共鸣",
      "ui_type": "UI_DIALOGUE",
      "text": "这是——我们大家的故事！！",
      "next_id": 10140082,
      "stay_time": 5,
      "priority": 1
    },
    "10140082": {
      "id": 10140082,
      "group_id": 1014002,
      "memo": "JQ01_洞窟_灵魂边境同行_小男孩７",
      "npc_icon": "Texture2D'/Game/NewRoco/Modules/System/BigMap/Raw/Atlas/WorldMapNpc/Frames/threshold_soul1.threshold_soul1'",
      "npc_name": "灵魂共鸣",
      "ui_type": "UI_DIALOGUE",
      "text": "如果生命迟早会燃烧殆尽，成为砂砾，成为尘埃",
      "next_id": 10140083,
      "stay_time": 5,
      "priority": 1
    },
    "10140083": {
      "id": 10140083,
      "group_id": 1014002,
      "memo": "JQ01_洞窟_灵魂边境同行_小男孩９",
      "npc_icon": "Texture2D'/Game/NewRoco/Modules/System/BigMap/Raw/Atlas/WorldMapNpc/Frames/threshold_soul2.threshold_soul2'",
      "npc_name": "灵魂共鸣",
      "ui_type": "UI_DIALOGUE",
      "text": "那我也会奢望，你和我的故事，在这个尽头里重生",
      "stay_time": 5,
      "priority": 1
    },
    "10140085": {
      "id": 10140085,
      "group_id": 1013005,
      "memo": "JQ01_洞窟_灵魂边境同行_里奥00（保底）",
      "npc_icon": "Texture2D'/Game/NewRoco/Modules/System/Common/Icon/HeadIcon/3397.3397'",
      "npc_name": "里奥",
      "ui_type": "UI_STATE",
      "text": "同行中…",
      "next_id": 10140086,
      "stay_time": 1,
      "priority": 1
    },
    "10140086": {
      "id": 10140086,
      "group_id": 1013005,
      "memo": "JQ01_洞窟_灵魂边境同行_里奥01",
      "npc_icon": "Texture2D'/Game/NewRoco/Modules/System/Common/Icon/HeadIcon/3397.3397'",
      "npc_name": "里奥",
      "ui_type": "UI_DIALOGUE",
      "text": "没想到，是它们……",
      "next_id": 10140087,
      "stay_time": 5,
      "priority": 1
    },
    "10140087": {
      "id": 10140087,
      "group_id": 1013005,
      "memo": "JQ01_洞窟_灵魂边境同行_里奥02",
      "npc_icon": "Texture2D'/Game/NewRoco/Modules/System/Common/Icon/HeadIcon/3397.3397'",
      "npc_name": "里奥",
      "ui_type": "UI_DIALOGUE",
      "text": "那些鸟儿是天空城的孩子",
      "next_id": 10140088,
      "stay_time": 5,
      "priority": 1
    },
    "10140088": {
      "id": 10140088,
      "group_id": 1013005,
      "memo": "JQ01_洞窟_灵魂边境同行_里奥03",
      "npc_icon": "Texture2D'/Game/NewRoco/Modules/System/Common/Icon/HeadIcon/3397.3397'",
      "npc_name": "里奥",
      "ui_type": "UI_DIALOGUE",
      "text": "它们正欢迎吾的归来",
      "next_id": 10140089,
      "stay_time": 5,
      "priority": 1
    },
    "10140089": {
      "id": 10140089,
      "group_id": 1013005,
      "memo": "JQ01_洞窟_灵魂边境同行_里奥04",
      "npc_icon": "Texture2D'/Game/NewRoco/Modules/System/Common/Icon/HeadIcon/3397.3397'",
      "npc_name": "里奥",
      "ui_type": "UI_DIALOGUE",
      "text": "大陆上每个生命逝去",
      "next_id": 10140090,
      "stay_time": 5,
      "priority": 1
    },
    "10140090": {
      "id": 10140090,
      "group_id": 1013005,
      "memo": "JQ01_洞窟_灵魂边境同行_里奥05",
      "npc_icon": "Texture2D'/Game/NewRoco/Modules/System/Common/Icon/HeadIcon/3397.3397'",
      "npc_name": "里奥",
      "ui_type": "UI_DIALOGUE",
      "text": "灵魂都会返回这里",
      "next_id": 10140091,
      "stay_time": 5,
      "priority": 1
    },
    "10140091": {
      "id": 10140091,
      "group_id": 1013005,
      "memo": "JQ01_洞窟_灵魂边境同行_里奥06",
      "npc_icon": "Texture2D'/Game/NewRoco/Modules/System/Common/Icon/HeadIcon/3397.3397'",
      "npc_name": "里奥",
      "ui_type": "UI_DIALOGUE",
      "text": "它们牺牲于灾厄之战",
      "next_id": 10140092,
      "stay_time": 5,
      "priority": 1
    },
    "10140092": {
      "id": 10140092,
      "group_id": 1013005,
      "memo": "JQ01_洞窟_灵魂边境同行_里奥07",
      "npc_icon": "Texture2D'/Game/NewRoco/Modules/System/Common/Icon/HeadIcon/3397.3397'",
      "npc_name": "里奥",
      "ui_type": "UI_DIALOGUE",
      "text": "从此便守候这片时空",
      "next_id": 10140093,
      "stay_time": 5,
      "priority": 1
    },
    "10140093": {
      "id": 10140093,
      "group_id": 1013005,
      "memo": "JQ01_洞窟_灵魂边境同行_里奥08",
      "npc_icon": "Texture2D'/Game/NewRoco/Modules/System/Common/Icon/HeadIcon/3397.3397'",
      "npc_name": "里奥",
      "ui_type": "UI_DIALOGUE",
      "text": "金色灵魂，纯粹的存在",
      "next_id": 10140094,
      "stay_time": 5,
      "priority": 1
    },
    "10140094": {
      "id": 10140094,
      "group_id": 1013005,
      "memo": "JQ01_洞窟_灵魂边境同行_里奥09",
      "npc_icon": "Texture2D'/Game/NewRoco/Modules/System/Common/Icon/HeadIcon/3397.3397'",
      "npc_name": "里奥",
      "ui_type": "UI_DIALOGUE",
      "text": "如果伊里斯能在这里",
      "next_id": 10140095,
      "stay_time": 5,
      "priority": 1
    },
    "10140095": {
      "id": 10140095,
      "group_id": 1013005,
      "memo": "JQ01_洞窟_灵魂边境同行_里奥10",
      "npc_icon": "Texture2D'/Game/NewRoco/Modules/System/Common/Icon/HeadIcon/3397.3397'",
      "npc_name": "里奥",
      "ui_type": "UI_DIALOGUE",
      "text": "也会同吾一般感动吧",
      "next_id": 10140096,
      "stay_time": 5,
      "priority": 1
    },
    "10140096": {
      "id": 10140096,
      "group_id": 1013005,
      "memo": "JQ01_洞窟_灵魂边境同行_里奥11（保底）",
      "npc_icon": "Texture2D'/Game/NewRoco/Modules/System/Common/Icon/HeadIcon/3397.3397'",
      "npc_name": "里奥",
      "ui_type": "UI_STATE",
      "text": "它们牺牲于灾厄之战",
      "stay_time": -1,
      "priority": 1
    },
    "10142003": {
      "id": 10142003,
      "group_id": 1034002,
      "memo": "A2拾遗-拉尔夫同行",
      "npc_name": "拉尔夫",
      "ui_type": "UI_DIALOGUE",
      "text": "……小地鼠为什么会独自出现在海滩呢？",
      "next_id": 10142004,
      "stay_time": 10,
      "priority": 1
    },
    "10142004": {
      "id": 10142004,
      "group_id": 1034002,
      "memo": "A2拾遗-拉尔夫同行",
      "npc_name": "拉尔夫",
      "ui_type": "UI_DIALOGUE",
      "text": "是因为之前被黑巫团成员掳走，受惊吓了吗？",
      "next_id": 10142005,
      "stay_time": 10,
      "priority": 1
    },
    "10142005": {
      "id": 10142005,
      "group_id": 1034002,
      "memo": "A2拾遗-拉尔夫同行",
      "npc_name": "拉尔夫",
      "ui_type": "UI_DIALOGUE",
      "text": "唉，之前就觉得小地鼠有些不对劲……",
      "next_id": 10142006,
      "stay_time": 10,
      "priority": 1
    },
    "10142006": {
      "id": 10142006,
      "group_id": 1034002,
      "memo": "A2拾遗-拉尔夫同行",
      "npc_name": "拉尔夫",
      "ui_type": "UI_DIALOGUE",
      "text": "但它怎么自己跑出去了，要是黑巫团的人再来了怎么办……",
      "next_id": 10142007,
      "stay_time": 10,
      "priority": 1
    },
    "10142007": {
      "id": 10142007,
      "group_id": 1034002,
      "memo": "A2拾遗-拉尔夫同行",
      "npc_name": "拉尔夫",
      "ui_type": "UI_DIALOGUE",
      "text": "它为什么不告诉我呢……",
      "stay_time": 10,
      "priority": 1
    },
    "10340001": {
      "id": 10340001,
      "group_id": 1034001,
      "memo": "A2拾遗-拉尔夫同行",
      "npc_name": "拉尔夫",
      "ui_type": "UI_STATE",
      "text": "同行中…",
      "next_id": 10340002,
      "stay_time": -1,
      "priority": 1
    },
    "10340002": {
      "id": 10340002,
      "group_id": 1034001,
      "memo": "A2拾遗-拉尔夫同行",
      "npc_name": "拉尔夫",
      "ui_type": "UI_DIALOGUE",
      "text": "你最后一次见到它，是在海滩？",
      "next_id": 10340003,
      "stay_time": 10,
      "condition": 5,
      "condition_parameter": [
        1
      ],
      "priority": 1
    },
    "10340003": {
      "id": 10340003,
      "group_id": 1034001,
      "memo": "A2拾遗-拉尔夫同行",
      "npc_name": "拉尔夫",
      "ui_type": "UI_DIALOGUE",
      "text": "……小地鼠为什么会独自出现在海滩呢？",
      "next_id": 10340004,
      "stay_time": 10,
      "priority": 1
    },
    "10340004": {
      "id": 10340004,
      "group_id": 1034001,
      "memo": "A2拾遗-拉尔夫同行",
      "npc_name": "拉尔夫",
      "ui_type": "UI_DIALOGUE",
      "text": "唉，之前就觉得小地鼠有些不对劲……",
      "next_id": 10340005,
      "stay_time": 10,
      "priority": 1
    },
    "10340005": {
      "id": 10340005,
      "group_id": 1034001,
      "memo": "A2拾遗-拉尔夫同行",
      "npc_name": "拉尔夫",
      "ui_type": "UI_DIALOGUE",
      "text": "但它怎么自己跑出去了，要是黑巫团的人再来了怎么办……",
      "next_id": 10340006,
      "stay_time": 10,
      "priority": 1
    },
    "10340006": {
      "id": 10340006,
      "group_id": 1034001,
      "memo": "A2拾遗-拉尔夫同行",
      "npc_name": "拉尔夫",
      "ui_type": "UI_DIALOGUE",
      "text": "到底发生什么了，你可千万不要有事啊……",
      "stay_time": 10,
      "priority": 1
    },
    "10340007": {
      "id": 10340007,
      "group_id": 1034001,
      "memo": "A2拾遗-拉尔夫同行",
      "npc_name": "拉尔夫",
      "ui_type": "UI_DIALOGUE",
      "stay_time": 10,
      "priority": 1
    },
    "10342001": {
      "id": 10342001,
      "group_id": 1034002,
      "memo": "A2拾遗-拉尔夫同行",
      "npc_name": "拉尔夫",
      "ui_type": "UI_STATE",
      "text": "同行中…",
      "next_id": 10342002,
      "stay_time": -1,
      "priority": 1
    },
    "10342002": {
      "id": 10342002,
      "group_id": 1034002,
      "memo": "A2拾遗-拉尔夫同行",
      "npc_name": "拉尔夫",
      "ui_type": "UI_DIALOGUE",
      "text": "你最后一次见到它，是在海滩？",
      "next_id": 10142003,
      "stay_time": 10,
      "condition": 5,
      "condition_parameter": [
        1
      ],
      "priority": 1
    },
    "52010111": {
      "id": 52010111,
      "group_id": 5201011,
      "memo": "拾遗登天之路-起点到微风",
      "npc_icon": "Texture2D'/Game/NewRoco/Modules/System/BigMap/Raw/Atlas/WorldMapNpc/Frames/10062.10062'",
      "npc_name": "恩佐",
      "ui_type": "UI_STATE",
      "text": "与恩佐同行中……",
      "stay_time": 3,
      "priority": 1
    },
    "52010112": {
      "id": 52010112,
      "group_id": 5201011,
      "memo": "拾遗登天之路-起点到微风",
      "npc_icon": "Texture2D'/Game/NewRoco/Modules/System/BigMap/Raw/Atlas/WorldMapNpc/Frames/10062.10062'",
      "npc_name": "恩佐",
      "ui_type": "UI_DIALOGUE",
      "text": "出发吧，先去试炼精灵原本在的地方看看。",
      "stay_time": 6,
      "condition": 3,
      "condition_parameter": [
        52010105,
        1
      ],
      "priority": 1
    },
    "52010121": {
      "id": 52010121,
      "group_id": 5201012,
      "memo": "拾遗登天之路-微风到狂风",
      "npc_icon": "Texture2D'/Game/NewRoco/Modules/System/BigMap/Raw/Atlas/WorldMapNpc/Frames/10062.10062'",
      "npc_name": "恩佐",
      "ui_type": "UI_STATE",
      "text": "与恩佐同行中……",
      "stay_time": 3,
      "priority": 1
    },
    "52010122": {
      "id": 52010122,
      "group_id": 5201012,
      "memo": "拾遗登天之路-微风到狂风",
      "npc_icon": "Texture2D'/Game/NewRoco/Modules/System/BigMap/Raw/Atlas/WorldMapNpc/Frames/10062.10062'",
      "npc_name": "恩佐",
      "ui_type": "UI_DIALOGUE",
      "text": "看样子，试炼精灵已经回来了，半山腰方向有噩梦气息。",
      "stay_time": 7,
      "condition": 3,
      "condition_parameter": [
        52010113,
        1
      ],
      "priority": 1
    },
    "52010131": {
      "id": 52010131,
      "group_id": 5201013,
      "memo": "拾遗登天之路-狂风到篝火",
      "npc_icon": "Texture2D'/Game/NewRoco/Modules/System/BigMap/Raw/Atlas/WorldMapNpc/Frames/10062.10062'",
      "npc_name": "恩佐",
      "ui_type": "UI_STATE",
      "text": "与恩佐同行中……",
      "stay_time": 3,
      "priority": 1
    },
    "52010132": {
      "id": 52010132,
      "group_id": 5201013,
      "memo": "拾遗登天之路-狂风到篝火",
      "npc_icon": "Texture2D'/Game/NewRoco/Modules/System/BigMap/Raw/Atlas/WorldMapNpc/Frames/10062.10062'",
      "npc_name": "恩佐",
      "ui_type": "UI_DIALOGUE",
      "text": "这座小山洞还算安全，就在这休息。",
      "next_id": 52010133,
      "stay_time": 5,
      "condition": 3,
      "condition_parameter": [
        52010123,
        1
      ],
      "priority": 1
    },
    "52010133": {
      "id": 52010133,
      "group_id": 5201013,
      "memo": "拾遗登天之路-狂风到篝火",
      "npc_icon": "Texture2D'/Game/NewRoco/Modules/System/BigMap/Raw/Atlas/WorldMapNpc/Frames/10062.10062'",
      "npc_name": "恩佐",
      "ui_type": "UI_DIALOGUE",
      "text": "篝火就拜托你了。",
      "stay_time": 5,
      "priority": 1
    },
    "52010141": {
      "id": 52010141,
      "group_id": 5201014,
      "memo": "拾遗登天之路-篝火到龙卷风",
      "npc_icon": "Texture2D'/Game/NewRoco/Modules/System/BigMap/Raw/Atlas/WorldMapNpc/Frames/10062.10062'",
      "npc_name": "恩佐",
      "ui_type": "UI_STATE",
      "text": "与恩佐同行中……",
      "stay_time": 3,
      "priority": 1
    },
    "52010142": {
      "id": 52010142,
      "group_id": 5201014,
      "memo": "拾遗登天之路-篝火到龙卷风",
      "npc_icon": "Texture2D'/Game/NewRoco/Modules/System/BigMap/Raw/Atlas/WorldMapNpc/Frames/10062.10062'",
      "npc_name": "恩佐",
      "ui_type": "UI_DIALOGUE",
      "text": "前面的路看起来很陡峭，小同学多加小心。",
      "stay_time": 6,
      "condition": 3,
      "condition_parameter": [
        52010127,
        1
      ],
      "priority": 1
    },
    "52010151": {
      "id": 52010151,
      "group_id": 5201015,
      "memo": "拾遗登天之路-龙卷风到终点",
      "npc_icon": "Texture2D'/Game/NewRoco/Modules/System/BigMap/Raw/Atlas/WorldMapNpc/Frames/10062.10062'",
      "npc_name": "恩佐",
      "ui_type": "UI_STATE",
      "text": "与恩佐同行中……",
      "stay_time": 3,
      "priority": 1
    },
    "52010152": {
      "id": 52010152,
      "group_id": 5201015,
      "memo": "拾遗登天之路-龙卷风到终点",
      "npc_icon": "Texture2D'/Game/NewRoco/Modules/System/BigMap/Raw/Atlas/WorldMapNpc/Frames/10062.10062'",
      "npc_name": "恩佐",
      "ui_type": "UI_DIALOGUE",
      "text": "好浓的噩梦能量……",
      "stay_time": 3,
      "condition": 3,
      "condition_parameter": [
        52010139,
        1
      ],
      "priority": 1
    },
    "100100201": {
      "id": 100100201,
      "group_id": 1001002,
      "memo": "测试条件用，FL_DEAFULT",
      "npc_icon": "Texture2D'/Game/NewRoco/Modules/System/BigMap/Raw/Atlas/WorldMapNpc/Frames/10047.10047'",
      "npc_name": "恩佐",
      "ui_type": "UI_STATE",
      "text": "正在同行中……",
      "stay_time": 3,
      "priority": 2
    },
    "100100204": {
      "id": 100100204,
      "group_id": 1001002,
      "memo": "对话",
      "npc_icon": "Texture2D'/Game/NewRoco/Modules/System/BigMap/Raw/Atlas/WorldMapNpc/Frames/10046.10046'",
      "npc_name": "伊里斯",
      "ui_type": "UI_DIALOGUE",
      "text": "呜哇，我怎么是个矮冬瓜？！感觉真臭！",
      "text_voice": "dialog201010550",
      "next_id": 100100205,
      "stay_time": 4,
      "priority": 3
    },
    "100100205": {
      "id": 100100205,
      "group_id": 1001002,
      "memo": "对话",
      "npc_icon": "Texture2D'/Game/NewRoco/Modules/System/BigMap/Raw/Atlas/WorldMapNpc/Frames/10046.10046'",
      "npc_name": "伊里斯",
      "ui_type": "UI_DIALOGUE",
      "text": "你们都比我帅多了，这个魔法怎么回事！",
      "text_voice": "dialog201010552",
      "next_id": 100100206,
      "stay_time": 4,
      "priority": 3
    },
    "100100206": {
      "id": 100100206,
      "group_id": 1001002,
      "memo": "对话",
      "npc_icon": "Texture2D'/Game/NewRoco/Modules/System/BigMap/Raw/Atlas/WorldMapNpc/Frames/10047.10047'",
      "npc_name": "恩佐",
      "ui_type": "UI_DIALOGUE",
      "text": "……嗯，你这个样子，看起来还挺顺眼的。",
      "text_voice": "dialog201010554",
      "next_id": 100100207,
      "stay_time": 4,
      "priority": 3
    },
    "100100207": {
      "id": 100100207,
      "group_id": 1001002,
      "memo": "对话",
      "npc_icon": "Texture2D'/Game/NewRoco/Modules/System/BigMap/Raw/Atlas/WorldMapNpc/Frames/10046.10046'",
      "npc_name": "伊里斯",
      "ui_type": "UI_DIALOGUE",
      "text": "恩佐，你故意的？！",
      "text_voice": "dialog201010556",
      "stay_time": 2,
      "priority": 3
    },
    "100100211": {
      "id": 100100211,
      "group_id": 1001002,
      "memo": "测试条件用，FL_DELETE",
      "npc_name": "伊里斯和恩佐",
      "ui_type": "UI_STATE",
      "text": "测试条件用，FL_DELETE",
      "stay_time": -1,
      "condition": 1,
      "priority": 1
    },
    "100100212": {
      "id": 100100212,
      "group_id": 1001002,
      "memo": "测试条件用，FL_OPTION",
      "npc_name": "伊里斯和恩佐",
      "ui_type": "UI_STATE",
      "text": "风场可以帮助你飞到更高的地方",
      "stay_time": -1,
      "condition": 2,
      "condition_parameter": [
        33375
      ],
      "priority": 1
    },
    "100100215": {
      "id": 100100215,
      "group_id": 1001002,
      "memo": "测试条件用，FL_BATTLE，进入战斗",
      "npc_name": "伊里斯和恩佐",
      "ui_type": "UI_STATE",
      "text": "测试条件用，FL_BATTLE，战斗成功",
      "stay_time": -1,
      "condition": 4,
      "condition_parameter": [
        332192,
        0
      ],
      "priority": 1
    },
    "100100216": {
      "id": 100100216,
      "group_id": 1001002,
      "memo": "测试条件用，FL_BATTLE，战斗胜利",
      "npc_name": "伊里斯和恩佐",
      "ui_type": "UI_STATE",
      "text": "测试条件用，FL_BATTLE，进入战斗",
      "stay_time": -1,
      "condition": 4,
      "condition_parameter": [
        10000067,
        1
      ],
      "priority": 1
    },
    "100100217": {
      "id": 100100217,
      "group_id": 1001002,
      "memo": "测试条件用，FL_BATTLE，战斗失败",
      "npc_name": "伊里斯和恩佐",
      "ui_type": "UI_STATE",
      "text": "测试条件用，FL_BATTLE，战斗失败",
      "stay_time": -1,
      "condition": 4,
      "condition_parameter": [
        51000067,
        2
      ],
      "priority": 1
    },
    "100100218": {
      "id": 100100218,
      "group_id": 1001002,
      "memo": "测试条件用，FL_TIME",
      "npc_name": "伊里斯和恩佐",
      "ui_type": "UI_STATE",
      "text": "你站在这里已经十分钟了……",
      "stay_time": -1,
      "condition": 5,
      "condition_parameter": [
        10
      ],
      "priority": 1
    },
    "100100219": {
      "id": 100100219,
      "group_id": 1001002,
      "memo": "测试条件用，FL_FASHION",
      "npc_name": "伊里斯和恩佐",
      "ui_type": "UI_STATE",
      "text": "这件衣服很好看",
      "stay_time": -1,
      "condition": 6,
      "condition_parameter": [
        21200401
      ],
      "priority": 1
    },
    "100100220": {
      "id": 100100220,
      "group_id": 1001002,
      "memo": "测试条件用，FL_WEATHER",
      "npc_name": "伊里斯和恩佐",
      "ui_type": "UI_STATE",
      "text": "天气变化了……",
      "stay_time": -1,
      "condition": 7,
      "condition_parameter": [
        3
      ],
      "priority": 1
    },
    "100100221": {
      "id": 100100221,
      "group_id": 1001002,
      "memo": "测试条件用，FL_PET",
      "npc_name": "伊里斯和恩佐",
      "ui_type": "UI_STATE",
      "text": "恭喜你获得新的精灵",
      "stay_time": -1,
      "condition": 8,
      "condition_parameter": [
        3028
      ],
      "priority": 1
    },
    "100100222": {
      "id": 100100222,
      "group_id": 1001002,
      "memo": "测试条件用，FL_EMOTE",
      "npc_name": "伊里斯和恩佐",
      "ui_type": "UI_STATE",
      "text": "你做这个动作是什么意思？",
      "stay_time": -1,
      "condition": 9,
      "condition_parameter": [
        1
      ],
      "priority": 1
    },
    "100100223": {
      "id": 100100223,
      "group_id": 1001002,
      "memo": "测试条件用，FL_REVIVE",
      "npc_name": "伊里斯和恩佐",
      "ui_type": "UI_STATE",
      "text": "测试条件用，FL_REVIVE",
      "stay_time": -1,
      "condition": 10,
      "priority": 1
    },
    "100100301": {
      "id": 100100301,
      "group_id": 1001003,
      "memo": "测试用，文案待补充",
      "npc_name": "恩佐",
      "ui_type": "UI_STATE",
      "text": "测试用，文案待补充",
      "stay_time": -1
    },
    "100100401": {
      "id": 100100401,
      "group_id": 1001004,
      "memo": "常态状态",
      "npc_name": "伊里斯",
      "ui_type": "UI_STATE",
      "text": "正在同行中……",
      "stay_time": -1,
      "priority": 1
    },
    "100200101": {
      "id": 100200101,
      "group_id": 1002001,
      "memo": "B1-JQ09-跟随恩佐去石碑",
      "npc_name": "恩佐",
      "ui_type": "UI_STATE",
      "text": "同行中……",
      "stay_time": -1,
      "priority": 1
    },
    "100200201": {
      "id": 100200201,
      "group_id": 1002002,
      "memo": "B1-JQ09-宿舍广场至生态社前",
      "npc_name": "恩佐",
      "ui_type": "UI_STATE",
      "text": "正在同行中……",
      "stay_time": -1,
      "priority": 1
    },
    "100200202": {
      "id": 100200202,
      "group_id": 1002002,
      "memo": "B1-JQ09-宿舍广场至生态社前-跟随对话1",
      "npc_name": "恩佐",
      "ui_type": "UI_DIALOGUE",
      "text": "【废弃】知愿石让你去生态园看看。",
      "stay_time": 5,
      "priority": 1
    },
    "100200203": {
      "id": 100200203,
      "group_id": 1002002,
      "memo": "B1-JQ09-宿舍广场至生态社前-跟随对话2",
      "npc_name": "恩佐",
      "ui_type": "UI_DIALOGUE",
      "text": "生态园是你们精灵学分院所属的教学区，最近还有一个打卡活动。",
      "next_id": 100200204,
      "stay_time": 5,
      "condition": 3,
      "condition_parameter": [
        80055012,
        1
      ],
      "priority": 1
    },
    "100200204": {
      "id": 100200204,
      "group_id": 1002002,
      "memo": "B1-JQ09-宿舍广场至生态社前-跟随对话3",
      "npc_name": "恩佐",
      "ui_type": "UI_DIALOGUE",
      "text": "我带你去吧。",
      "stay_time": 2,
      "priority": 1
    },
    "100200301": {
      "id": 100200301,
      "group_id": 1002003,
      "memo": "B1-JQ09-生态社到竞技场高台",
      "npc_name": "恩佐",
      "ui_type": "UI_STATE",
      "text": "同行中……",
      "stay_time": -1,
      "priority": 1
    },
    "100200302": {
      "id": 100200302,
      "group_id": 1002003,
      "memo": "B1-JQ09-生态社到竞技场高台-跟随对话1",
      "npc_name": "恩佐",
      "ui_type": "UI_DIALOGUE",
      "text": "竞技场的‘战斗考验’出了名的难，但奖励也相当丰厚。",
      "next_id": 100200303,
      "stay_time": 7,
      "condition": 2,
      "condition_parameter": [
        300200081
      ],
      "priority": 1
    },
    "100200303": {
      "id": 100200303,
      "group_id": 1002003,
      "memo": "B1-JQ09-生态社到竞技场高台-跟随对话2",
      "npc_name": "恩佐",
      "ui_type": "UI_DIALOGUE",
      "text": "得加快脚步了，听说现在那边正热闹着呢！",
      "stay_time": 7,
      "priority": 1
    },
    "100200401": {
      "id": 100200401,
      "group_id": 1002004,
      "memo": "B1-JQ09-竞技场广场到怪谈社浓雾区前-恩佐芙蕾雅跟随-默认",
      "npc_name": "恩佐和芙蕾雅",
      "ui_type": "UI_STATE",
      "text": "同行中……",
      "stay_time": -1,
      "priority": 1
    },
    "100200403": {
      "id": 100200403,
      "group_id": 1002004,
      "memo": "B1-JQ09-竞技场广场到怪谈社浓雾区前-恩佐芙蕾雅跟随-循环1",
      "npc_name": "恩佐",
      "ui_type": "UI_STATE",
      "text": "同行中……",
      "next_id": 100200404,
      "stay_time": 3,
      "condition": 3,
      "condition_parameter": [
        80055023,
        1
      ],
      "priority": 2
    },
    "100200404": {
      "id": 100200404,
      "group_id": 1002004,
      "memo": "B1-JQ09-竞技场广场到怪谈社浓雾区前-恩佐芙蕾雅跟随-循环2",
      "npc_icon": "Texture2D'/Game/NewRoco/Modules/System/BigMap/Raw/Atlas/WorldMapNpc/Frames/10270.10270'",
      "npc_name": "芙蕾雅",
      "ui_type": "UI_STATE",
      "text": "同行中……",
      "next_id": 100200403,
      "stay_time": 3,
      "condition": 5,
      "condition_parameter": [
        3
      ],
      "priority": 2
    },
    "100200501": {
      "id": 100200501,
      "group_id": 1002005,
      "memo": "B1-JQ09-怪谈社浓雾区到医生前-恩佐芙蕾雅跟随-默认",
      "npc_name": "恩佐和芙蕾雅",
      "ui_type": "UI_STATE",
      "text": "同行中……",
      "stay_time": -1,
      "priority": 1
    },
    "100200502": {
      "id": 100200502,
      "group_id": 1002005,
      "memo": "B1-JQ09-怪谈社浓雾区到医生前-恩佐芙蕾雅跟随-循环1",
      "npc_name": "恩佐",
      "ui_type": "UI_STATE",
      "text": "同行中……",
      "next_id": 100200503,
      "stay_time": 3,
      "condition": 5,
      "condition_parameter": [
        3
      ],
      "priority": 1
    },
    "100200503": {
      "id": 100200503,
      "group_id": 1002005,
      "memo": "B1-JQ09-怪谈社浓雾区到医生前-恩佐芙蕾雅跟随-循环2",
      "npc_icon": "Texture2D'/Game/NewRoco/Modules/System/BigMap/Raw/Atlas/WorldMapNpc/Frames/10270.10270'",
      "npc_name": "芙蕾雅",
      "ui_type": "UI_STATE",
      "text": "同行中……",
      "next_id": 100200502,
      "stay_time": 3,
      "priority": 2
    },
    "100200601": {
      "id": 100200601,
      "group_id": 1002006,
      "memo": "JQ10-芙蕾雅同行-怪谈社至学院大厅1F-仪式前",
      "npc_name": "芙蕾雅",
      "ui_type": "UI_STATE",
      "text": "同行中……",
      "stay_time": -1,
      "priority": 1
    },
    "100200602": {
      "id": 100200602,
      "group_id": 1002006,
      "memo": "JQ10-芙蕾雅同行-怪谈社至学院大厅1F-仪式前-台词1",
      "npc_name": "芙蕾雅",
      "ui_type": "UI_DIALOGUE",
      "text": "同行中……",
      "stay_time": 3,
      "condition": 3,
      "condition_parameter": [
        80056001,
        1
      ],
      "priority": 1
    },
    "100200603": {
      "id": 100200603,
      "group_id": 1002006,
      "memo": "JQ10-芙蕾雅同行-怪谈社至学院大厅1F-仪式前-台词2",
      "npc_name": "芙蕾雅",
      "ui_type": "UI_DIALOGUE",
      "text": "【废弃】哼，吃你的绩点，那是看得起你！",
      "next_id": 100200604,
      "stay_time": 3,
      "priority": 1
    },
    "100200604": {
      "id": 100200604,
      "group_id": 1002006,
      "memo": "JQ10-芙蕾雅同行-怪谈社至学院大厅1F-仪式前-台词3",
      "npc_name": "芙蕾雅",
      "ui_type": "UI_DIALOGUE",
      "text": "【废弃】换别人，想让我吃都没门儿！",
      "next_id": 100200605,
      "stay_time": 3,
      "priority": 1
    },
    "100200605": {
      "id": 100200605,
      "group_id": 1002006,
      "memo": "JQ10-芙蕾雅同行-怪谈社至学院大厅1F-仪式前-台词4",
      "npc_name": "芙蕾雅",
      "ui_type": "UI_DIALOGUE",
      "text": "【废弃】那个叫恩佐的家伙冷冰冰的，吃了他的绩点说不定会闹肚子！",
      "next_id": 100200606,
      "stay_time": 3,
      "priority": 1
    },
    "100200606": {
      "id": 100200606,
      "group_id": 1002006,
      "memo": "JQ10-芙蕾雅同行-怪谈社至学院大厅1F-仪式前-台词5",
      "npc_name": "芙蕾雅",
      "ui_type": "UI_DIALOGUE",
      "text": "【废弃】你的绩点嘛……看起来就特别顺眼，特别……温暖！",
      "stay_time": 3,
      "priority": 1
    },
    "100200801": {
      "id": 100200801,
      "group_id": 1002008,
      "memo": "JQ10-芙蕾雅同行-前往异常生态社-常规学院大厅、生态园",
      "npc_name": "芙蕾雅",
      "ui_type": "UI_STATE",
      "text": "同行中……",
      "stay_time": -1,
      "priority": 1
    },
    "100200901": {
      "id": 100200901,
      "group_id": 1002009,
      "memo": "JQ10-芙蕾雅同行-异常生态社内-生态园内（80057007完成结束）",
      "npc_name": "芙蕾雅",
      "ui_type": "UI_STATE",
      "text": "同行中……",
      "stay_time": -1,
      "priority": 1
    },
    "100200902": {
      "id": 100200902,
      "group_id": 1002009,
      "memo": "JQ10-芙蕾雅同行-异常生态社内-首次调药后台词1",
      "npc_name": "芙蕾雅",
      "ui_type": "UI_DIALOGUE",
      "text": "呼——终于能大口喘气了！",
      "stay_time": 3,
      "condition": 3,
      "condition_parameter": [
        80057004,
        0
      ],
      "priority": 1
    },
    "100200903": {
      "id": 100200903,
      "group_id": 1002009,
      "memo": "JQ10-芙蕾雅同行-异常生态社内-首次调药后台词2",
      "npc_name": "芙蕾雅",
      "ui_type": "UI_DIALOGUE",
      "text": "走吧，去找珂赛特老师算算账——",
      "stay_time": 3,
      "priority": 1
    },
    "100200904": {
      "id": 100200904,
      "group_id": 1002009,
      "memo": "JQ10-芙蕾雅同行-异常生态社内-首次调药后台词3",
      "npc_name": "芙蕾雅",
      "ui_type": "UI_DIALOGUE",
      "text": "咳咳，哦不，去解决她的问题！",
      "stay_time": 3,
      "priority": 1
    },
    "100200905": {
      "id": 100200905,
      "group_id": 1002009,
      "memo": "JQ10-芙蕾雅同行-异常生态社内-找猛犸象台词1",
      "npc_name": "芙蕾雅",
      "ui_type": "UI_DIALOGUE",
      "text": "这好像并不是毒雾……",
      "stay_time": 3,
      "condition": 3,
      "condition_parameter": [
        80057006,
        1
      ],
      "priority": 1
    },
    "100200906": {
      "id": 100200906,
      "group_id": 1002009,
      "memo": "JQ10-芙蕾雅同行-异常生态社内-找猛犸象台词2",
      "npc_name": "芙蕾雅",
      "ui_type": "UI_DIALOGUE",
      "text": "有一种很邪恶的气息……",
      "stay_time": 3,
      "priority": 1
    },
    "100200907": {
      "id": 100200907,
      "group_id": 1002009,
      "memo": "JQ10-芙蕾雅同行-异常生态社内-获得护心毛后-台词1",
      "npc_name": "芙蕾雅",
      "ui_type": "UI_DIALOGUE",
      "text": "走吧，去配制爱心药剂吧。",
      "stay_time": 5,
      "condition": 3,
      "condition_parameter": [
        80057007,
        1
      ],
      "priority": 1
    },
    "100201001": {
      "id": 100201001,
      "group_id": 1002010,
      "memo": "JQ10-芙蕾雅同行-异常生态社内-生态园内（80057009完成结束）遇到嘟嘟煲",
      "npc_name": "芙蕾雅",
      "ui_type": "UI_STATE",
      "text": "同行中……",
      "stay_time": -1,
      "priority": 1
    },
    "100201002": {
      "id": 100201002,
      "group_id": 1002010,
      "memo": "JQ10-芙蕾雅同行-异常生态社内-生态园内（80057009完成结束）遇到嘟嘟煲-默认",
      "npc_name": "芙蕾雅",
      "ui_type": "UI_STATE",
      "text": "同行中……",
      "next_id": 100201003,
      "stay_time": 3,
      "condition": 5,
      "condition_parameter": [
        5
      ],
      "priority": 1
    },
    "100201003": {
      "id": 100201003,
      "group_id": 1002010,
      "memo": "JQ10-芙蕾雅同行-异常生态社内-生态园内（80057009完成结束）遇到嘟嘟煲-循环1",
      "npc_icon": "Texture2D'/Game/NewRoco/Modules/System/Common/Icon/HeadIcon/3367.3367'",
      "npc_name": "嘟嘟煲",
      "ui_type": "UI_STATE",
      "text": "同行中……",
      "next_id": 100201002,
      "stay_time": 3,
      "priority": 1
    },
    "100201101": {
      "id": 100201101,
      "group_id": 1002011,
      "memo": "JQ10-芙蕾雅同行-异常生态社到竞技场-生态园、竞技场（80058002结束）",
      "npc_name": "芙蕾雅",
      "ui_type": "UI_STATE",
      "text": "同行中……",
      "stay_time": -1,
      "priority": 1
    },
    "100201102": {
      "id": 100201102,
      "group_id": 1002011,
      "memo": "JQ10-芙蕾雅同行-异常生态社到竞技场-到竞技场后台词1",
      "ui_type": "UI_DIALOGUE",
      "text": "哈？棋子不是用来玩的吗？",
      "stay_time": 5,
      "condition": 3,
      "condition_parameter": [
        80058001,
        0
      ],
      "priority": 1
    },
    "100201103": {
      "id": 100201103,
      "group_id": 1002011,
      "memo": "JQ10-芙蕾雅同行-异常生态社到竞技场-到竞技场后台词2",
      "ui_type": "UI_DIALOGUE",
      "text": "怎么开始攻击学生了！",
      "stay_time": 5,
      "priority": 1
    },
    "100201201": {
      "id": 100201201,
      "group_id": 1002012,
      "memo": "JQ10-芙蕾雅同行-怪谈社到礼拜教堂-怪谈社、礼拜教堂（80059004结束）",
      "npc_name": "芙蕾雅",
      "ui_type": "UI_STATE",
      "text": "同行中……",
      "stay_time": -1,
      "priority": 1
    },
    "101300100": {
      "id": 101300100,
      "group_id": 1013001,
      "memo": "黑巫师之影-跟随恶魔叮叮（首句）",
      "npc_icon": "Texture2D'/Game/NewRoco/Modules/System/BigMap/Raw/Atlas/WorldMapNpc/Frames/10062.10062'",
      "npc_name": "恩佐",
      "ui_type": "UI_STATE",
      "text": "同行中……",
      "stay_time": -1
    },
    "101300105": {
      "id": 101300105,
      "group_id": 1013001,
      "memo": "黑巫师之影-跟随恶魔叮叮",
      "npc_icon": "Texture2D'/Game/NewRoco/Modules/System/BigMap/Raw/Atlas/WorldMapNpc/Frames/10062.10062'",
      "npc_name": "恩佐",
      "ui_type": "UI_DIALOGUE",
      "text": "对了，你之前来过商店街吗？",
      "text_voice": "dialog101300105",
      "next_id": 101300110,
      "stay_time": 5,
      "condition": 5,
      "condition_parameter": [
        5
      ]
    },
    "101300110": {
      "id": 101300110,
      "group_id": 1013001,
      "memo": "黑巫师之影-跟随恶魔叮叮",
      "npc_icon": "Texture2D'/Game/NewRoco/Modules/System/BigMap/Raw/Atlas/WorldMapNpc/Frames/10062.10062'",
      "npc_name": "恩佐",
      "ui_type": "UI_DIALOGUE",
      "text": "这地方啊，总是人来人往，熙熙攘攘的。",
      "text_voice": "dialog101300110",
      "next_id": 101300115,
      "stay_time": 5
    },
    "101300115": {
      "id": 101300115,
      "group_id": 1013001,
      "memo": "黑巫师之影-跟随恶魔叮叮",
      "npc_icon": "Texture2D'/Game/NewRoco/Modules/System/BigMap/Raw/Atlas/WorldMapNpc/Frames/10062.10062'",
      "npc_name": "恩佐",
      "ui_type": "UI_DIALOGUE",
      "text": "怎么看都一副平静的模样。",
      "text_voice": "dialog101300115",
      "next_id": 101300120,
      "stay_time": 5
    },
    "101300120": {
      "id": 101300120,
      "group_id": 1013001,
      "memo": "黑巫师之影-跟随恶魔叮叮",
      "npc_icon": "Texture2D'/Game/NewRoco/Modules/System/BigMap/Raw/Atlas/WorldMapNpc/Frames/10062.10062'",
      "npc_name": "恩佐",
      "ui_type": "UI_DIALOGUE",
      "text": "可你知道，水面越平静，底下往往越藏着暗流。",
      "text_voice": "dialog101300120",
      "next_id": 101300190,
      "stay_time": 5
    },
    "101300190": {
      "id": 101300190,
      "group_id": 1013001,
      "memo": "黑巫师之影-跟随恶魔叮叮（尾句）",
      "npc_icon": "Texture2D'/Game/NewRoco/Modules/System/BigMap/Raw/Atlas/WorldMapNpc/Frames/10062.10062'",
      "npc_name": "恩佐",
      "ui_type": "UI_DIALOGUE",
      "text": "所以啊，我从不完全相信眼睛看到的东西，你呢？",
      "text_voice": "dialog101300190",
      "stay_time": 5
    },
    "101300200": {
      "id": 101300200,
      "group_id": 1013002,
      "memo": "黑巫师之影-追至噩梦祭坛（首句）",
      "npc_icon": "Texture2D'/Game/NewRoco/Modules/System/BigMap/Raw/Atlas/WorldMapNpc/Frames/10062.10062'",
      "npc_name": "恩佐",
      "ui_type": "UI_STATE",
      "text": "同行中……",
      "stay_time": -1
    },
    "101300205": {
      "id": 101300205,
      "group_id": 1013002,
      "memo": "黑巫师之影-追至噩梦祭坛",
      "npc_icon": "Texture2D'/Game/NewRoco/Modules/System/BigMap/Raw/Atlas/WorldMapNpc/Frames/10062.10062'",
      "npc_name": "恩佐",
      "ui_type": "UI_DIALOGUE",
      "text": "我和小猎犬曾追踪过一些形迹可疑的黑衣人。",
      "text_voice": "dialog101300205",
      "next_id": 101300210,
      "stay_time": 7,
      "condition": 5,
      "condition_parameter": [
        5
      ]
    },
    "101300210": {
      "id": 101300210,
      "group_id": 1013002,
      "memo": "黑巫师之影-追至噩梦祭坛",
      "npc_icon": "Texture2D'/Game/NewRoco/Modules/System/BigMap/Raw/Atlas/WorldMapNpc/Frames/10062.10062'",
      "npc_name": "恩佐",
      "ui_type": "UI_DIALOGUE",
      "text": "他们似乎经常在不远处的一片树林里接头。",
      "text_voice": "dialog101300210",
      "next_id": 101300215,
      "stay_time": 7
    },
    "101300215": {
      "id": 101300215,
      "group_id": 1013002,
      "memo": "黑巫师之影-追至噩梦祭坛",
      "npc_icon": "Texture2D'/Game/NewRoco/Modules/System/BigMap/Raw/Atlas/WorldMapNpc/Frames/10062.10062'",
      "npc_name": "恩佐",
      "ui_type": "UI_DIALOGUE",
      "text": "那里弥漫着一股浓郁的紫黑色力量，但最让我在意的是……",
      "text_voice": "dialog101300215",
      "next_id": 101300220,
      "stay_time": 7
    },
    "101300220": {
      "id": 101300220,
      "group_id": 1013002,
      "memo": "黑巫师之影-追至噩梦祭坛",
      "npc_icon": "Texture2D'/Game/NewRoco/Modules/System/BigMap/Raw/Atlas/WorldMapNpc/Frames/10062.10062'",
      "npc_name": "恩佐",
      "ui_type": "UI_DIALOGUE",
      "text": "在那片树林深处，我发现了一处从未见过的诡异祭坛。",
      "text_voice": "dialog101300220",
      "next_id": 101300290,
      "stay_time": 7
    },
    "101300290": {
      "id": 101300290,
      "group_id": 1013002,
      "memo": "黑巫师之影-追至噩梦祭坛（尾句）",
      "npc_icon": "Texture2D'/Game/NewRoco/Modules/System/BigMap/Raw/Atlas/WorldMapNpc/Frames/10062.10062'",
      "npc_name": "恩佐",
      "ui_type": "UI_DIALOGUE",
      "text": "想来，那大概就是他们口中的「圣坛」。",
      "text_voice": "dialog101300290",
      "stay_time": 7
    },
    "101300300": {
      "id": 101300300,
      "group_id": 1013003,
      "memo": "黑巫师之影-噩梦祭坛内（首句）",
      "npc_icon": "Texture2D'/Game/NewRoco/Modules/System/BigMap/Raw/Atlas/WorldMapNpc/Frames/10062.10062'",
      "npc_name": "恩佐",
      "ui_type": "UI_STATE",
      "text": "同行中……",
      "stay_time": -1
    },
    "101300302": {
      "id": 101300302,
      "group_id": 1013003,
      "memo": "黑巫师之影-噩梦祭坛内",
      "npc_icon": "Texture2D'/Game/NewRoco/Modules/System/BigMap/Raw/Atlas/WorldMapNpc/Frames/10062.10062'",
      "npc_name": "恩佐",
      "ui_type": "UI_DIALOGUE",
      "text": "奇怪，那个小家伙碰了一下石碑后，怎么消失不见了……",
      "text_voice": "dialog101300302",
      "next_id": 101300305,
      "stay_time": 5,
      "condition": 5,
      "condition_parameter": [
        5
      ]
    },
    "101300305": {
      "id": 101300305,
      "group_id": 1013003,
      "memo": "黑巫师之影-噩梦祭坛内",
      "npc_icon": "Texture2D'/Game/NewRoco/Modules/System/BigMap/Raw/Atlas/WorldMapNpc/Frames/10062.10062'",
      "npc_name": "恩佐",
      "ui_type": "UI_DIALOGUE",
      "text": "难道真如我所想，这个石碑背后，隐藏着一片未知的空间？",
      "text_voice": "dialog101300305",
      "next_id": 101300310,
      "stay_time": 5
    },
    "101300310": {
      "id": 101300310,
      "group_id": 1013003,
      "memo": "黑巫师之影-噩梦祭坛内",
      "npc_icon": "Texture2D'/Game/NewRoco/Modules/System/BigMap/Raw/Atlas/WorldMapNpc/Frames/10062.10062'",
      "npc_name": "恩佐",
      "ui_type": "UI_DIALOGUE",
      "text": "喂——小家伙，你能听到我的声音吗——",
      "text_voice": "dialog101300310",
      "next_id": 101300390,
      "stay_time": 5
    },
    "101300390": {
      "id": 101300390,
      "group_id": 1013003,
      "memo": "黑巫师之影-噩梦祭坛内（尾句）",
      "npc_icon": "Texture2D'/Game/NewRoco/Modules/System/BigMap/Raw/Atlas/WorldMapNpc/Frames/10062.10062'",
      "npc_name": "恩佐",
      "ui_type": "UI_DIALOGUE",
      "text": "唔，完全没反应啊。看来只能耐心等等了……",
      "text_voice": "dialog101300390",
      "stay_time": 5
    },
    "101300500": {
      "id": 101300500,
      "group_id": 1013004,
      "memo": "A2主线-立方人同行",
      "npc_icon": "Texture2D'/Game/NewRoco/Modules/System/Common/Icon/HeadIcon/3202.3202'",
      "npc_name": "驻地管家",
      "ui_type": "UI_STATE",
      "text": "同行中……",
      "stay_time": -1,
      "priority": 1
    },
    "101300501": {
      "id": 101300501,
      "group_id": 1013004,
      "memo": "A2主线-立方人同行",
      "npc_icon": "Texture2D'/Game/NewRoco/Modules/System/Common/Icon/HeadIcon/3202.3202'",
      "npc_name": "驻地管家",
      "ui_type": "UI_DIALOGUE",
      "text": "【导游模块启动】洛克里安安幅员辽阔，历史悠久。",
      "next_id": 101300502,
      "stay_time": 4,
      "condition": 3,
      "condition_parameter": [
        1015004,
        1
      ],
      "priority": 1
    },
    "101300502": {
      "id": 101300502,
      "group_id": 1013004,
      "memo": "A2主线-立方人同行",
      "npc_icon": "Texture2D'/Game/NewRoco/Modules/System/Common/Icon/HeadIcon/3202.3202'",
      "npc_name": "驻地管家",
      "ui_type": "UI_DIALOGUE",
      "text": "有着诸诸诸多城市——",
      "next_id": 101300503,
      "stay_time": 3,
      "priority": 1
    },
    "101300503": {
      "id": 101300503,
      "group_id": 1013004,
      "memo": "A2主线-立方人同行",
      "npc_icon": "Texture2D'/Game/NewRoco/Modules/System/Common/Icon/HeadIcon/3202.3202'",
      "npc_name": "驻地管家",
      "ui_type": "UI_DIALOGUE",
      "text": "王国城堡堡，是这里的核心。",
      "next_id": 101300504,
      "stay_time": 4,
      "priority": 1
    },
    "101300504": {
      "id": 101300504,
      "group_id": 1013004,
      "memo": "A2主线-立方人同行",
      "npc_icon": "Texture2D'/Game/NewRoco/Modules/System/Common/Icon/HeadIcon/3202.3202'",
      "npc_name": "驻地管家",
      "ui_type": "UI_DIALOGUE",
      "text": "南部机械工业，远超其他各省。",
      "next_id": 101300505,
      "stay_time": 3,
      "priority": 1
    },
    "101300505": {
      "id": 101300505,
      "group_id": 1013004,
      "memo": "A2主线-立方人同行",
      "npc_icon": "Texture2D'/Game/NewRoco/Modules/System/Common/Icon/HeadIcon/3202.3202'",
      "npc_name": "驻地管家",
      "ui_type": "UI_DIALOGUE",
      "text": "本机体即为成果之一一一",
      "stay_time": 3,
      "priority": 1
    },
    "421010101": {
      "id": 421010101,
      "group_id": 4210101,
      "memo": "S1赛季任务-地城-地牢1",
      "npc_icon": "Texture2D'/Game/NewRoco/Modules/System/BigMap/Raw/Atlas/WorldMapNpc/Frames/PEO_04904.PEO_04904'",
      "npc_name": "露萌",
      "ui_type": "UI_DIALOGUE",
      "text": "喂喂喂……能听到吗？",
      "text_voice": "dialog421010101",
      "next_id": 421010102,
      "stay_time": 3,
      "condition": 3,
      "condition_parameter": [
        60121007,
        1
      ],
      "priority": 1
    },
    "421010102": {
      "id": 421010102,
      "group_id": 4210101,
      "memo": "S1赛季任务-地城-地牢1",
      "npc_icon": "Texture2D'/Game/NewRoco/Modules/System/BigMap/Raw/Atlas/WorldMapNpc/Frames/PEO_04904.PEO_04904'",
      "npc_name": "露萌",
      "ui_type": "UI_DIALOGUE",
      "text": "终于连上了，第一次通信，我们之间的频率似乎错位，现在才同步上……",
      "text_voice": "dialog421010102",
      "next_id": 421010103,
      "stay_time": 3,
      "priority": 1
    },
    "421010103": {
      "id": 421010103,
      "group_id": 4210101,
      "memo": "S1赛季任务-地城-地牢1",
      "npc_icon": "Texture2D'/Game/NewRoco/Modules/System/BigMap/Raw/Atlas/WorldMapNpc/Frames/PEO_04904.PEO_04904'",
      "npc_name": "露萌",
      "ui_type": "UI_DIALOGUE",
      "text": "那是——「姐姐」？！虽然搞不清楚状况，快点跟上她吧。",
      "text_voice": "dialog421010103",
      "stay_time": 3,
      "priority": 1
    },
    "421010201": {
      "id": 421010201,
      "group_id": 4210102,
      "memo": "S1赛季任务-地城-研究员-地牢2",
      "npc_icon": "Texture2D'/Game/NewRoco/Modules/System/BigMap/Raw/Atlas/WorldMapNpc/Frames/PEO_04904.PEO_04904'",
      "npc_name": "露萌",
      "ui_type": "UI_DIALOGUE",
      "text": "唉，真是迷糊的性子。",
      "text_voice": "dialog421010201",
      "next_id": 421010202,
      "stay_time": 3,
      "condition": 3,
      "condition_parameter": [
        60121017,
        0
      ],
      "priority": 1
    },
    "421010202": {
      "id": 421010202,
      "group_id": 4210102,
      "memo": "S1赛季任务-地城-研究员-地牢2",
      "npc_icon": "Texture2D'/Game/NewRoco/Modules/System/BigMap/Raw/Atlas/WorldMapNpc/Frames/PEO_04904.PEO_04904'",
      "npc_name": "露萌",
      "ui_type": "UI_DIALOGUE",
      "text": "记忆里姐姐好像总是这样。",
      "text_voice": "dialog421010202",
      "next_id": 421010203,
      "stay_time": 3,
      "priority": 1
    },
    "421010203": {
      "id": 421010203,
      "group_id": 4210102,
      "memo": "S1赛季任务-地城-研究员-地牢2",
      "npc_icon": "Texture2D'/Game/NewRoco/Modules/System/BigMap/Raw/Atlas/WorldMapNpc/Frames/PEO_04904.PEO_04904'",
      "npc_name": "露萌",
      "ui_type": "UI_DIALOGUE",
      "text": "我们一起帮她找找吧。",
      "text_voice": "dialog421010203",
      "stay_time": 3,
      "priority": 1
    },
    "422010101": {
      "id": 422010101,
      "group_id": 4220101,
      "memo": "S1赛季任务-森林-露萌-刚进场景",
      "npc_icon": "Texture2D'/Game/NewRoco/Modules/System/BigMap/Raw/Atlas/WorldMapNpc/Frames/PEO_04904.PEO_04904'",
      "npc_name": "露萌",
      "ui_type": "UI_DIALOGUE",
      "text": "藏在山谷中的森林……",
      "text_voice": "dialog422010101",
      "next_id": 422010102,
      "stay_time": 3,
      "condition": 3,
      "condition_parameter": [
        60122007,
        0
      ],
      "priority": 1
    },
    "422010102": {
      "id": 422010102,
      "group_id": 4220101,
      "memo": "S1赛季任务-森林-露萌-刚进场景",
      "npc_icon": "Texture2D'/Game/NewRoco/Modules/System/BigMap/Raw/Atlas/WorldMapNpc/Frames/PEO_04904.PEO_04904'",
      "npc_name": "露萌",
      "ui_type": "UI_DIALOGUE",
      "text": "看样子，这个时候，她们应该已经成功逃离了地牢。",
      "text_voice": "dialog422010102",
      "next_id": 422010103,
      "stay_time": 3,
      "priority": 1
    },
    "422010103": {
      "id": 422010103,
      "group_id": 4220101,
      "memo": "S1赛季任务-森林-露萌-刚进场景",
      "npc_icon": "Texture2D'/Game/NewRoco/Modules/System/BigMap/Raw/Atlas/WorldMapNpc/Frames/PEO_04904.PEO_04904'",
      "npc_name": "露萌",
      "ui_type": "UI_DIALOGUE",
      "text": "姐姐就在旁边。像上次一样，要探索更多的记忆，我们去找她聊聊。",
      "text_voice": "dialog422010103",
      "stay_time": 3,
      "priority": 1
    },
    "422010201": {
      "id": 422010201,
      "group_id": 4220102,
      "memo": "S1赛季任务-森林-露萌-准备找果子",
      "npc_icon": "Texture2D'/Game/NewRoco/Modules/System/BigMap/Raw/Atlas/WorldMapNpc/Frames/PEO_04904.PEO_04904'",
      "npc_name": "露萌",
      "ui_type": "UI_DIALOGUE",
      "text": "找到森林里的魔力果，听起来还挺有意思的呢。",
      "text_voice": "dialog422010201",
      "next_id": 422010202,
      "stay_time": 3,
      "condition": 3,
      "condition_parameter": [
        60122009,
        1
      ],
      "priority": 1
    },
    "422010202": {
      "id": 422010202,
      "group_id": 4220102,
      "memo": "S2赛季任务-森林-露萌-准备找果子",
      "npc_icon": "Texture2D'/Game/NewRoco/Modules/System/BigMap/Raw/Atlas/WorldMapNpc/Frames/PEO_04904.PEO_04904'",
      "npc_name": "露萌",
      "ui_type": "UI_DIALOGUE",
      "text": "激活精灵视野就能找到长着果子的魔力果树。",
      "text_voice": "dialog422010202",
      "next_id": 422010203,
      "stay_time": 3,
      "priority": 1
    },
    "422010203": {
      "id": 422010203,
      "group_id": 4220102,
      "memo": "S3赛季任务-森林-露萌-准备找果子",
      "npc_icon": "Texture2D'/Game/NewRoco/Modules/System/BigMap/Raw/Atlas/WorldMapNpc/Frames/PEO_04904.PEO_04904'",
      "npc_name": "露萌",
      "ui_type": "UI_DIALOGUE",
      "text": "我怎么知道的？唔……唔……",
      "text_voice": "dialog422010203",
      "stay_time": 3,
      "priority": 1
    },
    "422010301": {
      "id": 422010301,
      "group_id": 4220103,
      "memo": "S1赛季任务-森林-露萌-发现果树摇不动",
      "npc_icon": "Texture2D'/Game/NewRoco/Modules/System/BigMap/Raw/Atlas/WorldMapNpc/Frames/PEO_04904.PEO_04904'",
      "npc_name": "露萌",
      "ui_type": "UI_DIALOGUE",
      "text": "光凭小帕尔的力量，还摘不下这些魔力果。",
      "text_voice": "dialog422010301",
      "next_id": 422010302,
      "stay_time": 3,
      "condition": 3,
      "condition_parameter": [
        60122011,
        1
      ],
      "priority": 1
    },
    "422010302": {
      "id": 422010302,
      "group_id": 4220103,
      "memo": "S1赛季任务-森林-露萌-发现果树摇不动",
      "npc_icon": "Texture2D'/Game/NewRoco/Modules/System/BigMap/Raw/Atlas/WorldMapNpc/Frames/PEO_04904.PEO_04904'",
      "npc_name": "露萌",
      "ui_type": "UI_DIALOGUE",
      "text": "既然如此，先去找姐姐会合吧。",
      "text_voice": "dialog422010302",
      "stay_time": 3,
      "priority": 1
    },
    "422010501": {
      "id": 422010501,
      "group_id": 4220105,
      "memo": "S1赛季-森林-露萌-回小屋",
      "npc_icon": "Texture2D'/Game/NewRoco/Modules/System/BigMap/Raw/Atlas/WorldMapNpc/Frames/PEO_04904.PEO_04904'",
      "npc_name": "露萌",
      "ui_type": "UI_DIALOGUE",
      "text": "游戏那么快就结束了，感觉还没玩够呢！",
      "stay_time": 3,
      "priority": 1
    },
    "423010101": {
      "id": 423010101,
      "group_id": 4230101,
      "memo": "S1赛季-农场-露萌-与小洛克玩耍（已废弃）",
      "npc_icon": "Texture2D'/Game/NewRoco/Modules/System/BigMap/Raw/Atlas/WorldMapNpc/Frames/PEO_04904.PEO_04904'",
      "npc_name": "露萌",
      "ui_type": "UI_DIALOGUE",
      "text": "S1赛季-农场-露萌-与小洛克玩耍（已废弃）",
      "stay_time": 3,
      "priority": 1
    },
    "423010102": {
      "id": 423010102,
      "group_id": 4230101,
      "memo": "S1赛季-农场-露萌-与小洛克玩耍（已废弃）",
      "npc_icon": "Texture2D'/Game/NewRoco/Modules/System/BigMap/Raw/Atlas/WorldMapNpc/Frames/PEO_04904.PEO_04904'",
      "npc_name": "露萌",
      "ui_type": "UI_DIALOGUE",
      "text": "S1赛季-农场-露萌-与小洛克玩耍（已废弃）",
      "stay_time": 3,
      "priority": 1
    },
    "423010103": {
      "id": 423010103,
      "group_id": 4230101,
      "memo": "S1赛季-农场-露萌-与小洛克玩耍（已废弃）",
      "npc_icon": "Texture2D'/Game/NewRoco/Modules/System/BigMap/Raw/Atlas/WorldMapNpc/Frames/PEO_04904.PEO_04904'",
      "npc_name": "露萌",
      "ui_type": "UI_DIALOGUE",
      "text": "S1赛季-农场-露萌-与小洛克玩耍（已废弃）",
      "stay_time": 3,
      "priority": 1
    },
    "423010201": {
      "id": 423010201,
      "group_id": 4230102,
      "memo": "S1赛季-农场-露萌-爬梯子",
      "npc_icon": "Texture2D'/Game/NewRoco/Modules/System/BigMap/Raw/Atlas/WorldMapNpc/Frames/PEO_04904.PEO_04904'",
      "npc_name": "露萌",
      "ui_type": "UI_DIALOGUE",
      "text": "这点高度的风车，对于帕尔萨斯来说根本不在话下。",
      "text_voice": "dialog301000060",
      "next_id": 423010202,
      "stay_time": 3,
      "condition": 3,
      "condition_parameter": [
        60123010,
        1
      ],
      "priority": 1
    },
    "423010202": {
      "id": 423010202,
      "group_id": 4230102,
      "memo": "S1赛季-农场-露萌-爬梯子",
      "npc_icon": "Texture2D'/Game/NewRoco/Modules/System/BigMap/Raw/Atlas/WorldMapNpc/Frames/PEO_04904.PEO_04904'",
      "npc_name": "露萌",
      "ui_type": "UI_DIALOGUE",
      "text": "你那健硕的四肢，只需要轻轻一跳……",
      "text_voice": "dialog301000061",
      "stay_time": 3,
      "priority": 1
    },
    "423010301": {
      "id": 423010301,
      "group_id": 4230103,
      "memo": "S1赛季-农场-露萌-结束战斗",
      "npc_icon": "Texture2D'/Game/NewRoco/Modules/System/BigMap/Raw/Atlas/WorldMapNpc/Frames/PEO_04904.PEO_04904'",
      "npc_name": "露萌",
      "ui_type": "UI_DIALOGUE",
      "text": "喂喂，怎么一下子都走了？真没意思。",
      "text_voice": "dialog301000062",
      "next_id": 423010302,
      "stay_time": 3,
      "condition": 3,
      "condition_parameter": [
        60123015,
        1
      ],
      "priority": 1
    },
    "423010302": {
      "id": 423010302,
      "group_id": 4230103,
      "memo": "S1赛季-农场-露萌-结束战斗",
      "npc_icon": "Texture2D'/Game/NewRoco/Modules/System/BigMap/Raw/Atlas/WorldMapNpc/Frames/PEO_04904.PEO_04904'",
      "npc_name": "露萌",
      "ui_type": "UI_DIALOGUE",
      "text": "姐姐的事应该也办的差不多了，我们回去看看好了！",
      "text_voice": "dialog301000063",
      "stay_time": 3,
      "priority": 1
    },
    "424010101": {
      "id": 424010101,
      "group_id": 4240101,
      "memo": "S1赛季-噩梦森林-刚进入场景",
      "npc_icon": "Texture2D'/Game/NewRoco/Modules/System/BigMap/Raw/Atlas/WorldMapNpc/Frames/PEO_04904.PEO_04904'",
      "npc_name": "露萌",
      "ui_type": "UI_DIALOGUE",
      "text": "姐姐就在那里，跟她聊聊吧。说不定能了解到更多的信息。",
      "text_voice": "dialog301000070",
      "stay_time": 3,
      "condition": 3,
      "condition_parameter": [
        60124002,
        1
      ],
      "priority": 1
    },
    "424010102": {
      "id": 424010102,
      "group_id": 4240101,
      "memo": "S2赛季-噩梦森林-刚进入场景（已废弃）",
      "npc_icon": "Texture2D'/Game/NewRoco/Modules/System/BigMap/Raw/Atlas/WorldMapNpc/Frames/PEO_04904.PEO_04904'",
      "npc_name": "露萌",
      "ui_type": "UI_DIALOGUE",
      "text": "S2赛季-噩梦森林-刚进入场景（已废弃）",
      "stay_time": 3,
      "priority": 1
    },
    "424010103": {
      "id": 424010103,
      "group_id": 4240101,
      "memo": "S2赛季-噩梦森林-刚进入场景（已废弃）",
      "npc_icon": "Texture2D'/Game/NewRoco/Modules/System/BigMap/Raw/Atlas/WorldMapNpc/Frames/PEO_04904.PEO_04904'",
      "npc_name": "露萌",
      "ui_type": "UI_DIALOGUE",
      "text": "S2赛季-噩梦森林-刚进入场景（已废弃）",
      "stay_time": 3,
      "priority": 1
    },
    "424010201": {
      "id": 424010201,
      "group_id": 4240102,
      "memo": "S1赛季-噩梦森林-露萌-进入森林",
      "npc_icon": "Texture2D'/Game/NewRoco/Modules/System/BigMap/Raw/Atlas/WorldMapNpc/Frames/PEO_04904.PEO_04904'",
      "npc_name": "露萌",
      "ui_type": "UI_DIALOGUE",
      "text": "好奇怪……天色变暗了。",
      "text_voice": "dialog301000072",
      "next_id": 424010202,
      "stay_time": 3,
      "condition": 3,
      "condition_parameter": [
        60124004,
        1
      ],
      "priority": 1
    },
    "424010202": {
      "id": 424010202,
      "group_id": 4240102,
      "memo": "S1赛季-噩梦森林露萌-进入森林",
      "npc_icon": "Texture2D'/Game/NewRoco/Modules/System/BigMap/Raw/Atlas/WorldMapNpc/Frames/PEO_04904.PEO_04904'",
      "npc_name": "露萌",
      "ui_type": "UI_DIALOGUE",
      "text": "突然感觉好难受……怎么回事？",
      "text_voice": "dialog301000073",
      "stay_time": 3,
      "priority": 1
    },
    "424010301": {
      "id": 424010301,
      "group_id": 4240103,
      "memo": "S1赛季-噩梦森林-露萌-进入森林2",
      "npc_icon": "Texture2D'/Game/NewRoco/Modules/System/BigMap/Raw/Atlas/WorldMapNpc/Frames/PEO_04904.PEO_04904'",
      "npc_name": "露萌",
      "ui_type": "UI_DIALOGUE",
      "text": "这些幻象到底是什么？为什么会出现在这里？",
      "text_voice": "dialog301000074",
      "next_id": 424010302,
      "stay_time": 3,
      "condition": 3,
      "condition_parameter": [
        60124005,
        1
      ],
      "priority": 1
    },
    "424010302": {
      "id": 424010302,
      "group_id": 4240103,
      "memo": "S1赛季-噩梦森林-露萌-进入森林2",
      "npc_icon": "Texture2D'/Game/NewRoco/Modules/System/BigMap/Raw/Atlas/WorldMapNpc/Frames/PEO_04904.PEO_04904'",
      "npc_name": "露萌",
      "ui_type": "UI_DIALOGUE",
      "text": "我的头有点痛……记忆……呜啊！",
      "text_voice": "dialog301000075",
      "stay_time": 3,
      "priority": 1
    },
    "424010401": {
      "id": 424010401,
      "group_id": 4240104,
      "memo": "S1赛季-噩梦森林--露萌-进入森林3(已废弃)",
      "npc_icon": "Texture2D'/Game/NewRoco/Modules/System/BigMap/Raw/Atlas/WorldMapNpc/Frames/PEO_04904.PEO_04904'",
      "npc_name": "露萌",
      "ui_type": "UI_DIALOGUE",
      "text": "S1赛季-噩梦森林--露萌-进入森林3(已废弃)",
      "next_id": 424010402,
      "stay_time": 3,
      "priority": 1
    },
    "424010402": {
      "id": 424010402,
      "group_id": 4240104,
      "memo": "S1赛季-噩梦森林--露萌-进入森林3(已废弃)",
      "npc_icon": "Texture2D'/Game/NewRoco/Modules/System/BigMap/Raw/Atlas/WorldMapNpc/Frames/PEO_04904.PEO_04904'",
      "npc_name": "露萌",
      "ui_type": "UI_DIALOGUE",
      "text": "S1赛季-噩梦森林--露萌-进入森林3(已废弃)",
      "stay_time": 3,
      "priority": 1
    }
  },
  "LocalizationStrings": {}
}